Workbook

Sheet 表紙
A1: RFP添付資料3_要求機能一覧
B5: 提案会社名 | D5: 株式会社システムインテグレータ | J5: ←社名を記入ください
A8: 記入要綱
B9: 貴社記入欄「実現方法」に「標準」「アドオン・カスタマイズ」「不可」のいずれかを回答ください。
B10: 「回答詳細」欄に回答内容を記載ください。
B11: 「実現方法」で「アドオン・カスタマイズ」を選択した場合、「アドオン・カスタマイズ概算費用」を記載ください。
B12: DFDに沿って記載しているため、同じ要求機能が複数行に記載されています。その場合は、「連番〇〇〇と同じ」
B13: と回答詳細に記載下さい。「実現方法」は設定ください。
B15: 全て、シートに直接入力をお願いします。
B16: 備考欄に質問を記入して送り返すことはしないでください。
B17: 質問はまとめて、別途質問シートにて提出を願いします。
B18: 記入された内容について、詳細かつ明瞭に記述してください。
B19: 会社名を必ず入力してください。
B20: 「必須/OP」欄について、「必須」は必須機能、「OP」はオプション機能を意味します。

Sheet 要求機能一覧
A3: 当社記入欄 | I3: 貴社記入欄（実現方法）
A4: 連番 | B4: Lv1 | C4: Lv2 | D4: 処理ID | E4: 処理名 | F4: システム要件 | G4: 必須 /OP | H4: 帳票 | I4: 実現方法 | J4: 回答詳細 | K4: アドオン・カスタマイズ 概算費用（円） | L4: メモ | M4: Aド標準 B運用変更 C運用負荷大 | N4: 北勝/玉置 | O4: 機能名
A5: 1 | B5: 1.購買 | C5: 1.所要量計算 | D5: 1.1 | E5: 生産計画入力 | F5: 月次生産計画を入力する | G5: 必須 | I5: 標準 | J5: 月次、週次、日次単位で生産計画を入力する機能を具備しております。 | K5: - | M5: A | N5: 北勝
A6: 2 | B6: 1.購買 | C6: 1.所要量計算 | D6: 1.2 | E6: 所要量計算 | F6: 入力された生産計画に基づき、在庫を踏まえ生産に必要な半製品・部材・資材の手配数を計算する 処理が軽量で、日中でも十分活用できるパフォーマンスが出ること 所要量計算処理において、月次処理へ影響しないシミュレーションができること 以下の要件も満たすこと ・確定期間（Time Fence）の設定 ・在庫の再引当（引当変更）機能 ・需要に対する優先順位付け機能 または、（運用）定期的な引当の見直し ・MRPの柔軟な実行制御 資材所要量計画（MRP）を必要に応じて任意タイミングで実行可能とする ・月次処理との共存運用 締処理・伝票管理とMRP実行を相互に干渉させないスケジューリング機能を有するもの ・計画と手配の即時連携 生産計画入力後、即座に資材展開・所要確認が行われること ・仮計画ベースでのMRPシミュレーション機能の導入 なお、先行手配が必要な品目（例えば、半導体）は、通常品とは異なることが区分けできる区分を品目マスタに設定でき、先行手配のための所要量計算ができること ・子部品からの逆展開 子部品の現在庫から親品目（最終製品）がいくら製造できるか逆展開で所要量計算できること | G6: 必須 | I6: 標準 | J6: 確定期間の設定、在庫の再引当機能、 需要に対する優先順位付け機能を具備しております。 また、定期的な引当見直しは特定条件下で実行が可能です。 MRPは任意のタイミングで、月次処理と相互に干渉なく実行することができます。 生産計画入力は即時反映され、資材展開・所要量確認ができます。 仮計画ベースでのMRPシミュレーション、先行手配品の所要量計算にも対応しております。 子部品からの逆展開について、BOM展開と在庫情報の組み合わせによる間接的な確認が可能です。 | K6: - | L6: 1JW（拡張ATP）追加ライセンス | M6: B | N6: 北勝
A7: 3 | B7: 1.購買 | C7: 2.発注検討 | D7: 2.1 | E7: 発注検討書出力 | F7: 発注の要否、および、発注日、発注数量を検討するための帳票を出力する | G7: 必須 | H7: 〇 | I7: 標準 | J7: 従来の紙ベースの帳票に代わり、リアルタイムの在庫・所要状況を可視化し、発注の意思決定を支援する対話型の機能が標準で提供されています。 また、各アプリには、表示されているリストをそのままExcel形式でダウンロードする機能が標準で備わっています。 | K7: - | M7: B | N7: 北勝
A8: 4 | B8: 1.購買 | C8: 2.発注検討 | D8: 2.2 | E8: 発注検討・承認 | F8: 発注検討結果を承認する | G8: 必須 | I8: 標準 | J8: MRPや手動で作成された購買依頼（PR）に対し、ワークフロー機能を用いた承認プロセスを標準で備えています。 | K8: - | M8: A | N8: 北勝
A9: 5 | B9: 1.購買 | C9: 2.発注検討 | D9: 2.3 | E9: 品目別在庫照会 | F9: 品目別の在庫状況を画面に出力する なお、現時点の在庫情報の照会だけでなく、 PSI（生産（Production）、販売（Sales）、在庫（Inventory））の推移を、将来の在庫推移（入荷予定・生産予定・出荷予定）を踏まえて、在庫推移が照会できること | G9: 必須 | I9: 標準 | J9: 品目別の在庫照会機能を具備しております。 生産・販売・在庫で個別の推移確認が可能です。 複数のアプリケーションを効果的に組み合わせた運用により、入荷予定・生産予定・出荷予定を踏まえたPSI推移の照会が可能となり、実用的なレベルでのPSI推移管理が実現できます。 | K9: - | M9: B | N9: 北勝
A10: 6 | B10: 1.購買 | C10: 3.発注 | D10: 3.1 | E10: 発注書発行 | F10: 発注書及び当社指定納品書も発行する （外貨が扱えること） | G10: 必須 | H10: 〇 | I10: アドオン・カスタマイズ | J10: 標準帳票での運用ができないと判断された場合にはアドオン開発が必要です。 | K10: 800000 | N10: 北勝 | O10: 指定納品書
A11: 7 | B11: 1.購買 | C11: 3.発注 | D11: 3.2 | E11: 楽々明細連携 | F11: 基幹システムから発行された書面を所定の取引先へ送付するために楽々明細へ送信する | G11: 必須 | I11: アドオン・カスタマイズ | J11: 外部サービスへ連携するためのアドオン開発が必要です。 添付資料9の「社内・社外間IF一覧」に記載されている仕入先向けの注文書および納品書、得意先向けの作業報告書および納品書を対象に当要件でのお見積とします。 | K11: 7200000 | N11: 北勝 | O11: 注文書楽楽連携 仕入先納品書楽楽連携 作業報告書楽楽連携 得意先納品書楽楽連携
A12: 8 | B12: 1.購買 | C12: 3.発注 | D12: 3.3 | E12: 納期回答受領 | F12: 納期回答をデータとして受信する 発注数が多い仕入先には一部機能を公開し、直接納期回答を入力してもらう または、対応できる仕入先においては、EDIによるデータ連携も可能とする | G12: 必須 | I12: アドオン・カスタマイズ | J12: SAPの標準機能には、特定の仕入先向けに納期回答用の専用画面を直接公開する機能および納期回答データを受信する機能は具備されていないため、アドオン開発が必要です。 EDI/データ連携：システム間連携が可能な仕入先とは、SAPの標準APIを用いて納期回答を直接受信し、購買発注データへ自動反映させることを想定しています。 ポータル画面に代わる運用：特定の仕入先向けに専用画面を構築・公開する手法は、開発・維持コストの観点から推奨いたしません。代替として、SAPの発注情報をメールやデータ（Excel等）で送付し、仕入先からの回答をAsteriaを活用してシステムへ取り込む運用を想定しています。 | K12: 3000000 | L12: SAP Business Network | N12: 北勝 | O12: 納期回答データEDI取込 納期回答データファイル取込
A13: 9 | B13: 1.購買 | C13: 4.受入 | D13: 4.1 | E13: 入荷実績入力 | F13: 購買発注した部材・資材の入荷実績を入力する 今回導入する現場システム（HTT）と基幹システムがデータ連携できること 現場での受け払いに係る入力は、現場システム（ハンディターミナル）を用いて行う そのため、現品には、品目を特定するためのバーコードが貼り付けられ、各種指示や伝票には、指示を特定するためにバーコードが印刷されていること 基幹システムと現場システムとは、人を介さず、自動でデータ連携できること | G13: 必須 | I13: アドオン・カスタマイズ | J13: ハンディターミナルによる仕入入庫データを取り込む機能のアドオン開発が必要です。 | K13: 1500000 | L13: ラベル印刷(F1563) Scope Item：3HQ | N13: 北勝 | O13: ハンディ仕入入庫データ取込
A14: 10 | B14: 1.購買 | C14: 4.受入 | D14: 4.1a | E14: 納入予定データ受信 | F14: 仕入先よりEDI経由で納入予定データを受信する | G14: 任意 | I14: アドオン・カスタマイズ | J14: EDI経由でデータを取り込むためのアドオン開発が必要です。 | K14: 1500000 | N14: 北勝 | O14: 納入予定データEDI取込
A15: 11 | B15: 1.購買 | C15: 4.受入 | D15: 4.2 | E15: 仕入入力 | F15: 仕入処理にて、仕入仕訳が自動で発生すること （5.4.1参照） （外貨が扱えること） よって、受入処理（倉庫側）と仕入処理（購買または経理） ※支払通知書で運用している。（請求書照合は行っていない） 課税・非課税は、仕入先単位での設定 （外貨が扱えること） | G15: 必須 | I15: 標準 | J15: 以下の機能を具備しております。 ・受入処理（入庫）および仕入処理（請求書照合または自動振替）の会計仕訳のリアルタイム自動生成 ・請求書照合不要の「支払通知書」運用 ・仕入先ごとの柔軟な税・外貨対応 | K15: - | M15: A | N15: 北勝
A16: 12 | B16: 1.購買 | C16: 5.支給指示 | D16: 5.1 | E16: 支給予定照会 | F16: 外注加工先への支給予定を画面に出力する なお、有償支給・無償支給において、以下の対応ができること 無償支給： MRPにより支給数が算出され、支給指示書としてまとめる （複数の支給先があろうと、必要なときに必要な数量は算出される） 有償支給： 当社主導）支給数は上記の通り算出され、支給指示書を発行する_x000B_ 先方手動）支給先の支給依頼（発注）に基づいて支給する | G16: 必須 | I16: 標準 | J16: 無償支給・有償支給ともに標準機能を具備しております。 MRP連動の支給数算出、支給指示、有償支給に対する債権相殺まで対応しております。 | K16: - | M16: A | N16: 北勝
A17: 13 | B17: 1.購買 | C17: 5.支給指示 | D17: 5.2 | E17: 支給指示書発行 | F17: 外注加工先への支給指示書を出力する 外注加工手配および支給品の手配も、所要量計算の対象とする 人手による作業を軽減するために、個装単位等、ロットまとめ方式など、所要量計算で対応できること ・外注加工の手配も所要量計算の対象とし、所要量計算の結果、どの外注加工先に、どの品目をいつまでに、いくつ生産しなければならないかが明確になります。 ・支給数も所要量計算の対象とし、その外注加工手配に基づいて、所要量計算後、部品数とその場合のリール数を算出されます。なお、リールについては、個装単位を設けることで、１リールあたりの部品点数が予め登録されているため、部品数に基づいてリール数が算出されます | G17: 必須 | H17: 〇 | I17: 標準 | J17: 支給指示書発行機能、およびMRP実行による外注加工と支給品の管理機能、基本的な単位換算機能を具備しております。 | K17: - | M17: A | N17: 北勝
A18: 14 | B18: 1.購買 | C18: 6.支給 | D18: 6.1 | E18: 支給実績入力 | F18: 外注加工先への支給実績を入力する 外注加工先への材料直送実績の入力について、以下の選択肢が選択できること なお、５は、取引先様にてご協力いただけない場合の対応方法 １．仕入先（材料業者）に支給実績を入力してもらう（入力画面の提供） ２．仕入先（加工業者）に受領実績を入力してもらう（入力画面の提供） ３．仕入先（材料業者）から支給実績データを提供いただく（EDI） ４．仕入先（加工業者）から受領実績データを提供いただく（EDI） ５．当社にて一括登録 | G18: 必須 | I18: アドオン・カスタマイズ | J18: SAPの標準機能には、特定の取引先向けに専用画面を直接公開する機能は具備されていないため、アドオン開発が必要です。 EDI/データ連携：システム間連携が可能な取引先とは、SAPの標準APIを用いて実績情報を直接受信し、SAP上で実績計上することを想定しています。 ポータル画面に代わる運用：特定の取引先向けに専用画面を構築・公開する手法は、開発・維持コストの観点から推奨いたしません。代替として、SAPの発注情報をメールやデータ（Excel等）で送付し、取引先からの実績情報をAsteriaを活用してシステムへ取り込む運用を想定しています。 | K18: 3000000 | N18: 北勝 | O18: 支給実績データEDI取込 支給実績データファイル取込
A19: 15 | B19: 1.購買 | C19: 6.支給 | D19: 6.2 | E19: 移動指示書発行 | F19: 社内の在庫移動の指示書を発行する なお、計画外の在庫移動（数量変更）は、承認を得るように、ワークフローが実装できること | G19: 必須 | H19: 〇 | I19: 標準 | J19: 在庫転送オーダーに基づく在庫移動指示書の発行機能および 計画外の数量変更や移動に対する承認機能を具備しております。 | K19: - | M19: A | N19: 北勝
A20: 16 | B20: 1.購買 | C20: 6.支給 | D20: 6.3 | E20: 移動実績入力 | F20: 社内の在庫移動結果を入力する | G20: 必須 | I20: 標準 | J20: プラント間移動、保管場所間移動、在庫ステータス変更などの実績入力を行う機能を具備しております。 | K20: - | M20: A | N20: 北勝
A21: 17 | B21: 2.製造 | C21: 1.年間計画 | D21: 1.1 | E21: 年間生産計画立案 | F21: 年間生産計画を立案する 年次計画の策定においては、販売・製造する製品の仕様が定まっていない場合があるため、製品カテゴリ単位で、代表品目を設定し、その代表品目（カテゴリ品目）を用いて立案することで対応できること 生産計画の立案において、備忘情報として、改造情報（from-to）や数量変更情報等の定性情報がメモできること 海外子会社との生産計画の共有において、現行システム（出荷システム）を用いて行っている。引き続き、当該システムを利用するため、自動でデータ連携が行えること | G21: 必須 | I21: アドオン・カスタマイズ | J21: 計画用品目や製品グループ機能により、仕様未定段階でのカテゴリ単位の立案に対応します。 計画展開後の各トランザクションにテキストを保持する機能を具備しております。 現行システム（出荷システム）との自動データ連携については、アドオン開発が必要です。 | K21: 1500000 | L21: 生産計画管理にテキストあり。 | N21: 北勝 | O21: 生産計画データ送信
A22: 18 | B22: 2.製造 | C22: 2.生産計画（月次） | D22: 2.1 | E22: 年間生産計画修正 | F22: 立案された年間生産計画を修正する 生産計画の立案において、備忘情報として、改造情報（from-to）や数量変更情報等の定性情報がメモできること | G22: 必須 | I22: 標準 | J22: 計画独立所要量（PIR）の修正・更新に対応しており、即座に後続のMRPへ反映可能です。 計画展開後の各トランザクションにテキストを保持する機能を具備しております。 | K22: - | L22: 生産計画管理にテキストあり。 | M22: A | N22: 北勝
A23: 19 | B23: 2.製造 | C23: 2.生産計画（月次） | D23: 2.2 | E23: 生産実績反映 | F23: 月次生産計画を立案するために、生産実績を反映する | G23: 必須 | I23: 標準 | J23: 実績を考慮した計画立案を行う独立需要計画（PIR）とMRP機能を具備しております。 | K23: - | M23: A | N23: 北勝
A24: 20 | B24: 2.製造 | C24: 2.生産計画（月次） | D24: 2.3 | E24: 月次生産計画立案 | F24: 月次生産計画を立案する | G24: 必須 | I24: 標準 | J24: 月次、週次、日次単位で生産計画を入力する機能を具備しております。 | K24: - | M24: A | N24: 北勝
A25: 21 | B25: 2.製造 | C25: 3.所要量計算 | D25: 3.1 | E25: 生産計画入力 | F25: 1.1.1と同じ | G25: 必須 | I25: 標準 | J25: 連番1と同じ | K25: - | M25: A | N25: 北勝
A26: 22 | B26: 2.製造 | C26: 3.所要量計算 | D26: 3.2 | E26: 所要量計算 | F26: 1.1.2と同じ | G26: 必須 | I26: 標準 | J26: 連番2と同じ | K26: - | M26: B | N26: 北勝
A27: 23 | B27: 2.製造 | C27: 3.所要量計算 | D27: 3.2a | E27: 能力計算 | F27: 所要量計算処理後、リソース（設備・人）の能力を考慮した能力計画ができること | G27: 必須 | I27: 標準 | J27: 単純な負荷確認から、ガントチャートを用いたドラッグ＆ドロップによるリスケジュール、さらには高度な自動スケジューリングまで、要件の複雑さに応じた標準機能が具備しております。 | K27: - | M27: A | N27: 北勝
A28: 24 | B28: 2.製造 | C28: 3.所要量計算 | D28: 3.3 | E28: 注文書発行 | F28: 発注書及び当社指定納品書も発行する | G28: 必須 | H28: 〇 | I28: アドオン・カスタマイズ | J28: 連番6と同じ | K28: - | N28: 北勝 | O28: -
A29: 25 | B29: 2.製造 | C29: 3.所要量計算 | D29: 3.4 | E29: 使用部品一覧表発行 | F29: 製造に必要な半製品・部材の使用一覧を出力する | G29: 必須 | H29: 〇 | I29: 標準 | J29: 製品を作るために必要な部材を多階層で一覧出力する機能を具備しております。 | K29: - | M29: A | N29: 北勝
A30: 26 | B30: 2.製造 | C30: 3.所要量計算 | D30: - | E30: 部品構成マスタ | F30: 部品構成表に代替品・同等品が登録でき、優先度、有効期限、在庫消化切り替えの基準にて、代替品・同等品への切り替えが行える機能が実装されていること 部品構成表の中に、代替品（同等品）の登録ができ、かつ、優先順位も設定できること。 また、後継品への切り替え時にも当該機能を用いることで、予め部品構成として登録することで、切替時の煩雑さの軽減を期待できる 現行の課題を解消するために、以下の要件が必要と考えます。 ・同等品グループを予め登録し、当該グループに登録している品目の優先度が設定でき、優先度に応じて調達が必要な品目が設定される ・同等品グループに登録されている品目の有効期限を設けることで、後継品の切り替え時期として利用できる ・後継品への切り替えにあたり、旧部材の在庫がなくなった時点で、後継品に切り替える | G30: 必須 | I30: 標準 | J30: 登録している品目の優先度を設定し、優先度に応じて調達が必要な品目を設定する機能を具備しております。 同等品の有効期限設定についてはBOMのバージョン管理を後継品切り替え時期としての利用に対応しています。 また旧部材の在庫がなくなった時点での後継品への自動切り替え機能を標準で具備しております。 | K30: - | M30: B | N30: 北勝
A31: 27 | B31: 2.製造 | C31: 4.製造指示 | D31: 4.1 | E31: 製造指示書発行 | F31: 製造指示書をは出力する | G31: 必須 | H31: 〇 | I31: 標準 | J31: 製造指図書の出力機能を具備しております。 | K31: - | M31: A | N31: 北勝
A32: 28 | B32: 2.製造 | C32: 5.ピッキング指示 | D32: 5.1 | E32: ピッキングリスト発行 | F32: ピッキングリストを出力する | G32: 必須 | H32: 〇 | I32: 標準 | J32: 出荷伝票、生産計画からのピッキングリストの出力機能を具備しております。 | K32: - | M32: A | N32: 北勝
A33: 29 | B33: 2.製造 | C33: 5.ピッキング指示 | D33: 5.2 | E33: 出庫実績入力 | F33: 社内の在庫移動（出庫）結果を入力する なお、在庫の受け払いにおいては、払出側・受入側に分けて、実績入力できること（2Step）。 但し、払出側・受入側の実績入力を求めず、実績入力することで、払出側・受入側が同時に実行される処理（1Step）も選択できること | G33: 必須 | I33: 標準 | J33: 業務要件や倉庫間の距離に応じて、1回の入力で移動を完了させる方式(Step1)か、払出と受入を分けて管理する方式(Step2)かを柔軟に選択可能です。 | K33: - | M33: A | N33: 北勝
A34: 30 | B34: 2.製造 | C34: 6.製造 | D34: 6.1 | E34: 製造実績入力 | F34: 製造実績（生産数、使用部品数）を入力する 製品の出来高を入力することで、構成品の消費量を理論値で引き落とすバックフラッシュ機能が具備されていること。 また、製造実績の入力においては、現場システム（ハンディターミナル等）が扱えること | G34: 必須 | I34: アドオン・カスタマイズ | J34: バックフラッシュ機能を具備しております。 ハンディターミナルによる生産入庫データを取り込む機能のアドオン開発が必要です。 | K34: 1500000 | N34: 北勝 | O34: ハンディ生産入庫データ取込
A35: 31 | B35: 3.在庫 | C35: 1.在庫照会 | D35: 1.1 | E35: 在庫照会 | F35: 1.2.3も含まれる。品目別注文残照会・引当状況照会も実現 | G35: 必須 | I35: 標準 | J35: 品目別注文残照会・引当状況照会を標準機能にて具備しております。 PSI推移の時系列分析機能については複数のアプリケーションを効果的に組み合わせた運用により、入荷予定・生産予定・出荷予定を踏まえたPSI推移の照会が可能となり、実用的なレベルで実現できます。 | K35: - | M35: B | N35: 北勝
A36: 32 | B36: 3.在庫 | C36: 2.出庫 | D36: 2.1 | E36: ピッキングリスト発行 | F36: 2.5.1と同じ | G36: 必須 | H36: 〇 | I36: 標準 | J36: 出荷伝票、生産計画からのピッキングリストの出力機能を具備しております。 | K36: - | M36: A | N36: 北勝
A37: 33 | B37: 3.在庫 | C37: 2.出庫 | D37: 2.4 | E37: 出庫実績入力 | F37: 2.5.2と同じ HTT（ハンディーターミナル）への出庫指示の送信 HTTによる出庫実績入力および基幹システムへの送信 | G37: 必須 | I37: アドオン・カスタマイズ | J37: ハンディターミナルへ出庫指示データを送信する機能のアドオン開発が必要です。 | K37: 1500000 | N37: 北勝 | O37: ハンディ出庫指示データ送信
A38: 34 | B38: 3.在庫 | C38: 2.出庫 | D38: 2.7 | E38: 移動実績入力 | F38: 1.6.3と同じ HTT（ハンディーターミナル）への移動指示の送信 HTTによる移動実績入力および基幹システムへの送信 | G38: 必須 | H38: 〇 | I38: アドオン・カスタマイズ | J38: ハンディターミナルによる移動実績データを取り込む機能のアドオン開発が必要です。 | K38: 1500000 | N38: 北勝 | O38: ハンディ移動実績データ取込
A39: 35 | B39: 3.在庫 | C39: 2.出庫 | D39: 2.8 | E39: 移動指示書発行 | F39: 1.6.2と同じ HTT（ハンディーターミナル）への移動指示の送信 | G39: 必須 | I39: アドオン・カスタマイズ | J39: ハンディターミナルへ移動指示データを送信する機能のアドオン開発が必要です。 | K39: 1500000 | N39: 北勝 | O39: ハンディ移動指示データ送信
A40: 36 | B40: 3.在庫 | C40: 2.出庫 | D40: 2.1 | E40: 支給指示書（リスト）発行 | F40: 1.5.2と同じ HTT（ハンディーターミナル）への支給指示の送信 | G40: 必須 | H40: 〇 | I40: アドオン・カスタマイズ | J40: ハンディターミナルへ支給指示データを送信する機能のアドオン開発が必要です。 | K40: 1500000 | N40: 北勝 | O40: ハンディ支給指示データ送信
A41: 37 | B41: 3.在庫 | C41: 2.出庫 | D41: 2.11 | E41: 支給実績入力 | F41: 1.5.3と同じ HTTによる支給（出庫）実績入力および基幹システムへの送信 （支給品の消費は、外注加工品の入荷時の処理） | G41: 必須 | I41: アドオン・カスタマイズ | J41: ハンディターミナルによる支給実績データを取り込む機能のアドオン開発が必要です。 | K41: 1500000 | N41: 北勝 | O41: ハンディ支給実績データ取込
A42: 38 | B42: 3.在庫 | C42: 3.入庫（入荷） | D42: 3.2 | E42: 入荷実績入力 | F42: 1.4.1と同じ HTT（ハンディーターミナル）への入荷予定の送信 HTTによる入荷実績入力および基幹システムへの送信 | G42: 必須 | I42: アドオン・カスタマイズ | J42: 連番9と同じ | K42: - | N42: 北勝 | O42: -
A43: 39 | B43: 3.在庫 | C43: 3.入庫（入荷） | D43: 3.3 | E43: 現品票発行 | F43: 現物に貼り付ける現品票を出力する 現品ラベルの貼り付け作業を引き受けていただける仕入先・外注先向けに、予め現品ラベルを送付できること。または、仕入先・外注先に提供するラベル発行アプリを提供する | G43: 必須 | H43: 〇 | I43: アドオン・カスタマイズ | J43: SAP標準機能では購買発注情報に基づく現品票出力機能は具備されていないため、アドオン開発が必要です。 SAP上の購買発注データをAsteriaが取得し、あらかじめ定義した現品票レイアウト（バーコード等を含む）に従ってPDFを自動生成する想定です。 | K43: 800000 | L43: SAP Business Network ラベル印刷(F1563) Scope Item：3HQ | N43: 北勝 | O43: 現品票
A44: 40 | B44: 3.在庫 | C44: 4.棚卸 | D44: 4.1 | E44: 棚卸リスト作成 | F44: 実地棚卸のための棚卸一覧を出力する HTT（ハンディーターミナル）への棚卸しリストの送信 循環棚卸もできるように | G44: 必須 | H44: 〇 | I44: アドオン・カスタマイズ | J44: ハンディターミナルへ棚卸データを送信する機能のアドオン開発が必要です。 | K44: 1500000 | N44: 北勝 | O44: ハンディ棚卸データ送信
A45: 41 | B45: 3.在庫 | C45: 4.棚卸 | D45: 4.3 | E45: 棚卸結果入力 | F45: 実地棚卸結果を入力する HTTによる棚卸結果の入力および基幹システムへの送信 | G45: 必須 | I45: アドオン・カスタマイズ | J45: ハンディターミナルによる棚卸データを取り込む機能のアドオン開発が必要です。 | K45: 1500000 | N45: 北勝 | O45: ハンディ棚卸データ取込
A46: 42 | B46: 3.在庫 | C46: 5.共通 | D46: 5.1 | E46: シリアル番号管理 | F46: 以下の機能が実現できること １．マスタ管理機能： 品目マスタ、シリアル番号採番ルール設定、シリアル番号マスタ ２．実績収集・登録機能： 製造実績登録、親子関係登録、検査実績登録 ３．在庫管理機能： シリアル番号別在庫照会、シリアル番号指定入出庫、シリアル棚卸 ４．トレーサビリティ機能： トレースフォワード（正引き）機能、トレースバック（逆引き）機能 | G46: 必須 | I46: 標準 | J46: いずれも標準機能として具備しております。 | K46: - | M46: A | N46: 北勝
A47: 43 | B47: 3.在庫 | C47: - | D47: - | E47: 在庫状態管理 | F47: 在庫の状態管理をステータスではなく場所コードで行う運用を次期システムでも継続できること | G47: 必須 | I47: 標準 | J47: 保管場所ベースの在庫管理機能を具備しております。 | K47: - | M47: A | N47: 北勝
A48: 44 | B48: 3.在庫 | C48: - | D48: - | E48: 在庫シミュレーション | F48: 未登録案件を含む将来の入庫予定・出庫予定を事前に入力できること | G48: 必須 | I48: 標準 | J48: 独立需要計画（PIR）機能を活用することで、販売予測や計画需要をMRP運算に反映させ、原材料需要量の計算に活用することができます。 | K48: - | M48: A | N48: 北勝
A49: 45 | B49: 3.在庫 | C49: - | D49: - | E49: 在庫シミュレーション | F49: 入力した入出庫予定をもとに、品番ごとの在庫推移（在庫残高・引当状況）を 将来日付までシミュレーションできること。 | G49: 必須 | I49: 標準 | J49: 将来の入出庫予定（受注、製造指図、購買発注、計画独立所要量など）をリアルタイムに集計し、将来の特定の日付における在庫残高を動的に算出・表示する機能を具備しております。 | K49: - | L49: 標準としているが、外部連携するならアドオン・カスタマイズ | M49: C | N49: 北勝
A50: 46 | B50: 3.在庫 | C50: - | D50: - | E50: 在庫シミュレーション | F50: 品番ごとの日別入出庫表をシステム上で確認できること | G50: 必須 | I50: 標準 | J50: 品目、日付にて入出庫伝票を抽出する機能を具備しております。 | K50: - | L50: 入出庫伝票概要 | M50: A | N50: 北勝
A51: 47 | B51: 3.在庫 | C51: - | D51: - | E51: 在庫シミュレーション | F51: 将来の在庫不足・引当不足を判定でき、必要に応じて警告等のアラート表示を行えること。 | G51: 必須 | I51: 標準 | J51: 安全在庫を下回る場合の自動検出・通知機能を具備しております。 | K51: - | L51: 状況処理 | M51: A | N51: 北勝
A52: 48 | B52: 4.販売 | C52: 2.受注 | D52: 2.4 | E52: 受注入力 | F52: 大量受注に対し、複数年にわたる分納計画を登録・管理できること | G52: 必須 | I52: 標準 | J52: 納入日程を分けて登録する機能を具備しております。 | K52: - | M52: A | N52: 玉置
A53: 49 | B53: 4.販売 | C53: 2.受注 | D53: 2.4 | E53: 受注入力 | F53: 納期未定の受注であっても、受注残をシステム上で管理できること | G53: 必須 | I53: 標準 | J53: 納入日程日は必須項目となりますが、遠い先日付を登録することで、納期未定であるか識別いただけます。 | K53: - | M53: B | N53: 玉置
A54: 50 | B54: 4.販売 | C54: 2.受注 | D54: 2.4 | E54: 受注入力 | F54: 受注数量の変更に柔軟に対応できること | G54: 必須 | I54: 標準 | J54: 登録済みの受注伝票を編集する機能を具備しておりますので、受注数量を変更いただけます。 | K54: - | M54: A | N54: 玉置
A55: 51 | B55: 4.販売 | C55: 2.受注 | D55: 2.4 | E55: 受注入力 | F55: 単価はロット単価で管理できること | G55: 必須 | I55: 標準 | J55: ロット単価を販売ロットと理解したうえで回答いたします。 受注時に受注数量にあわせたスケール単価を初期セットする機能を具備しております。 | K55: - | M55: A | N55: 玉置
A56: 52 | B56: 4.販売 | C56: 2.受注 | D56: 2.4 | E56: 受注入力 | F56: 受注確度が低い段階でも、客先情報なしで受注(仮)を登録できること | G56: 必須 | I56: 標準 | J56: 得意先に対する見積機能を具備しております。見積機能にてダミー受注先に対して登録することで、仮の受注を登録いただけます。 | K56: - | M56: A | N56: 玉置
A57: 53 | B57: 4.販売 | C57: 2.受注 | D57: 2.4 | E57: 受注入力 | F57: 設計未確定の場合、仮の品目（ダミー品番）で受注登録できること | G57: 必須 | I57: 標準 | J57: ダミー品番とわかる品目をマスタへ事前登録しておき、それを使用して受注登録いただけます。 誤って出荷が行われないようにストップをかける機能を具備しております。 | K57: - | M57: A | N57: 玉置
A58: 54 | B58: 4.販売 | C58: 2.受注 | D58: 2.4 | E58: 受注入力 | F58: 受注変更時にシステム上で承認処理が行えること | G58: 必須 | I58: 標準 | J58: 新規登録に加え、変更時に承認フローが処理される機能を具備しております。 | K58: - | M58: A | N58: 玉置
A59: 55 | B59: 4.販売 | C59: 2.受注 | D59: 2.4 | E59: 受注入力 | F59: MOQ未満の受注を、基幹システム上で登録・共有できること | G59: 必須 | I59: 標準 | J59: MOQ未満の受注である場合、アラートメッセージを表示する機能を具備しております。 アラート機能であるため、システム上は登録いただけます。 | K59: - | M59: A | N59: 玉置
A60: 56 | B60: 4.販売 | C60: 2.受注 | D60: 2.4 | E60: 受注入力 | F60: 受注情報（変更履歴・MOQ未満情報）を社内で一元管理できること | G60: 必須 | I60: 標準 | J60: 受注情報の変更ログを照会する機能を具備しております。 また、汎用的な項目を追加する機能を具備しておりますので、MOQ未満の場合はフラグ付けすることで一元的に管理いただけます。 | K60: - | M60: B | N60: 玉置
A61: 57 | B61: 4.販売 | C61: 2.受注 | D61: 2.4 | E61: 受注入力 | F61: 受注登録時に品目名を上書きできること | G61: 必須 | I61: 標準 | J61: 品目名はマスタで登録されている名称が初期セットされますが、編集する機能を具備しております。 | K61: - | M61: A | N61: 玉置
A62: 58 | B62: 4.販売 | C62: 2.受注 | D62: 2.6 | E62: PI登録・印刷(海外) | F62: Proforma Invoice を修正可能な帳票として出力できること | G62: 必須 | H62: 〇 | I62: アドオン・カスタマイズ | J62: 修正可能な帳票として出力する機能は標準では具備していないため、帳票をExcel出力するアドオン開発が必要です。 | K62: 800000 | N62: 玉置 | O62: Profoma Invoice
A63: 59 | B63: 4.販売 | C63: 2.受注 | D63: ー | E63: 案件管理 | F63: 工事を含むレジャーサービスでは、案件（プロジェクト）を新規登録・更新・参照できること。 | G63: 任意 | I63: 標準 | J63: 工事管理に適したプロジェクト管理モジュールを具備しております。 | K63: - | L63: EPPM使用想定 | M63: A | N63: 玉置
A64: 60 | B64: 4.販売 | C64: 2.受注 | D64: ー | E64: 案件管理 | F64: 案件に紐づく売上・原価・粗利を自動集計できること。 | G64: 任意 | I64: 標準 | J64: プロジェクトの細分化単位である「WBS要素」を管理する機能具備しております。 WBS要素と受注を紐づける機能を具備しておりますので、案件の売上や費用を紐づけて把握いただけます。 | K64: - | L64: EPPM使用想定 | M64: A | N64: 玉置
A65: 61 | B65: 4.販売 | C65: 2.受注 | D65: ー | E65: 案件管理 | F65: 案件に対し、商品・外注費・工事費など複数の受注明細を紐づけて管理できること。 | G65: 任意 | I65: 標準 | J65: 受注明細をWBS要素に紐づける機能を具備しております。 | K65: - | L65: EPPM使用想定 | M65: A | N65: 玉置
A66: 62 | B66: 4.販売 | C66: 2.受注 | D66: ー | E66: 案件管理 | F66: 受注登録時に案件を選択できること。案件未登録の場合、受注登録画面から案件を新規作成できること。ただし、案件を使用せずに受注登録もできること | G66: 任意 | I66: 標準 | J66: WBS要素を選択する機能を具備しております。また、WBS要素は必須項目ではなく任意項目となります。 | K66: - | L66: EPPM使用想定 | M66: A | N66: 玉置
A67: 63 | B67: 4.販売 | C67: 2.受注 | D67: ー | E67: 案件管理 | F67: 案件に対して外注費・工事費を原価として登録できること | G67: 任意 | I67: 標準 | J67: 案件で発生した費用を原価としてWBS要素に計上する機能を具備しております。 | K67: - | L67: EPPM使用想定 | M67: A | N67: 玉置
A68: 64 | B68: 4.販売 | C68: 2.受注 | D68: ー | E68: 案件管理 | F68: 案件ステータス（受注済／工事中／完了／請求済）を管理できること | G68: 任意 | I68: 標準 | J68: 「作成・リリース（仕掛中）・完了・終了」という単位でプロジェクトのステータスを管理する機能を具備しております。 | K68: - | L68: EPPM使用想定 | M68: A | N68: 玉置
A69: 65 | B69: 4.販売 | C69: 3.前受請求 | D69: 3.3 | E69: 前受請求書作成依頼 | F69: 受注情報を起点として、前受請求書の申請・承認・作成までをシステム上で実行できること | G69: 必須 | H69: 〇 | I69: 標準 | J69: 受注と紐づけた前受請求書を登録する請求計画機能を具備しております。 また、前受請求書は仮請求伝票として登録することで承認処理を行う機能を具備しております。 | K69: - | L69: BD9＋BKJに合わせて、仮請求伝票のワークフロー通せばいけそう。実機触った結果承認だけ謎に飛ばないけどアプリはある。 | M69: C | N69: 玉置
A70: 66 | B70: 4.販売 | C70: 3.前受請求 | D70: 3.4 | E70: 前受請求書作成依頼 | F70: 前受請求書は、一式での金額および名称の変更が可能であること。前受請求書の一式出力は、請求書と同様の仕様とする。 | G70: 必須 | H70: 〇 | I70: アドオン・カスタマイズ | J70: 受注と紐づけた前受請求書を登録する請求計画機能を具備しており、前受請求書に係る金額や名称を変更するには請求計画を修正する必要があります。 標準帳票での運用ができないと判断された場合には帳票のアドオン開発が必要となります。 | K70: 800000 | M70: A | N70: 玉置 | O70: 前受請求書
A71: 67 | B71: 4.販売 | C71: 3.前受請求 | D71: 3.4 | E71: 前受請求書作成 | F71: 前受金の管理をシステム上で行えること。 | G71: 必須 | I71: 標準 | J71: 前受金の発生、残高、消込を管理する機能を具備しております。 | K71: - | M71: A | N71: 玉置
A72: 68 | B72: 4.販売 | C72: 3.前受請求 | D72: 3.4 | E72: 前受請求書作成 | F72: 外貨建て取引において、前受金の管理が可能であること。 | G72: 必須 | I72: 標準 | J72: 外貨建て取引であっても、前受金を管理する機能を具備しております。 | K72: - | M72: A | N72: 玉置
A73: 69 | B73: 4.販売 | C73: 3.前受請求 | D73: 3.4 | E73: 前受請求書作成 | F73: 受注登録時に「前受」かどうかを設定可能とし、また、同一得意先コードで前受の有無をマスタで一元管理できること | G73: 必須 | I73: 標準 | J73: 受注登録時に前受金の設定を行う機能を具備しております。 得意先に対する前受金の有無のマスタ管理については、汎用的な項目を追加する機能にて対応することを想定しております。 | K73: - | M73: B | N73: 玉置
A74: 70 | B74: 4.販売 | C74: 4.出荷 | D74: 4.3 | E74: 在庫引当 | F74: 出荷日や納期を考慮した自動引当ロジックを導入し、優先順位に応じた在庫引当が可能であること | G74: 必須 | I74: 標準 | J74: 優先順位判定ルールは 顧客優先度、納期緊急度、オーダー金額による重み付け計算に対応しています。 | K74: - | L74: 追加ライセンス1JW（拡張ATP） | M74: A | N74: 北勝
A75: 71 | B75: 4.販売 | C75: 4.出荷 | D75: 4.3 | E75: 在庫引当 | F75: 引当後でも引当内容を変更でき、横入対応が可能であること | G75: 必須 | I75: 標準 | J75: 販売伝票の引当管理機能により引当後の内容変更が可能で、優先度設定機能により基本的な横入対応も実現できます。 | K75: - | L75: 追加ライセンス1JW（拡張ATP） | M75: A | N75: 北勝
A76: 72 | B76: 4.販売 | C76: 4.出荷 | D76: 4.3 | E76: 在庫引当 | F76: 倉庫の優先順をシステム上で簡易に変更できること | G76: 必須 | I76: 標準 | J76: 保管場所の優先順位付け、一つの倉庫（プラント）に在庫がない場合、自動的に他の倉庫を探しに行く設定機能を具備しております。 | K76: - | L76: 追加ライセンス1JW（拡張ATP） | M76: A | N76: 北勝
A77: 73 | B77: 4.販売 | C77: 4.出荷 | D77: 4.4 | E77: 出荷指示依頼 | F77: 受注情報をもとに出荷指図をシステム上で生成できること | G77: 必須 | I77: 標準 | J77: 標準機能として具備しております。 | K77: - | L77: Scope Item: 18J | M77: A | N77: 北勝
A78: 74 | B78: 4.販売 | C78: 4.出荷 | D78: 4.4 | E78: 出荷指示依頼 | F78: 在庫の有無にかかわらず、出荷に関する情報（出荷予定および出荷指示書）をシステム上で登録・作成・管理できること | G78: 必須 | H78: 〇 | I78: 標準 | J78: 在庫有無に関わらず出荷予定情報の登録を行う出荷伝票の登録および処理機能を具備しております。 | K78: - | M78: A | N78: 北勝
A79: 75 | B79: 4.販売 | C79: 4.出荷 | D79: 4.5 | E79: 出荷指示書発行 | F79: 出荷指示書に必要な情報（長文コメント等）を追加できること | G79: 必須 | H79: 〇 | I79: 標準 | J79: 出荷伝票にカスタムフィールドとして長文コメント等を追加する機能および標準帳票を調整する機能を具備しております。 | K79: - | N79: 北勝
A80: 76 | B80: 4.販売 | C80: 4.出荷 | D80: 4.5 | E80: 出荷指示書発行 | F80: ケースマーク、ドライバー受領書などの関連ファイルを出荷指示書に添付できること | G80: 必須 | H80: 〇 | I80: 標準 | J80: ケースマーク・ドライバー受領書等のファイルを出荷伝票に添付することは可能ですが、選択的な添付ファイル送信機能には制限があるため、運用ルールでの補完や段階的な機能拡張を検討することを推奨します。 | K80: - | M80: B | N80: 北勝
A81: 77 | B81: 4.販売 | C81: 4.出荷 | D81: 4.13 | E81: 貸出処理 | F81: 貸出品をシステム上で登録・管理できること | G81: 必須 | I81: 標準 | J81: 得意先預託品管理の機能を具備しております。 | K81: - | L81: 1IU | M81: A | N81: 北勝
A82: 78 | B82: 4.販売 | C82: 4.出荷 | D82: 4.13 | E82: 貸出処理 | F82: 貸出後に返却された品目をB級品としてステータス管理できること | G82: 必須 | I82: 標準 | J82: 預託在庫から自社倉庫へ戻す「預託品引取」のステップにおいて、入庫時の在庫ステータスを指定する機能を具備しております。 | K82: - | L82: 1IU | M82: A | N82: 北勝
A83: 79 | B83: 4.販売 | C83: 4.出荷 | D83: 4.13 | E83: 貸出処理 | F83: 貸出後に返却されず売却となる場合、売上計上基準に従い、値引き価格で売上登録できること | G83: 必須 | I83: 標準 | J83: 預託品出庫（売却）プロセスにおいて、値引き価格での売上登録を行う機能を具備しております。 | K83: - | L83: 1IU | M83: A | N83: 北勝
A84: 80 | B84: 4.販売 | C84: 4.出荷 | D84: 4.14 | E84: 売却処理 | F84: 貸出品が売却された場合は在庫から除外し、売上計上すること。 | I84: 標準 | J84: 預託品出庫 (売却)プロセスを実行することで、貸出品を自社資産から除外し、売却として処理する機能を具備しております。出庫転記により在庫が引き落とされた後、後続の請求書登録を行うことで売上と売掛金が財務会計に正しく計上されます 。 | K84: - | L84: 1IU | M84: A | N84: 北勝
A85: 81 | B85: 4.販売 | C85: 4.出荷 | D85: 4.16 | E85: B級品管理 | F85: 返却された品目をB級品在庫として登録・管理できること | G85: 必須 | I85: 標準 | J85: 連番78と同じ | K85: - | L85: 1IU | M85: A | N85: 北勝
A86: 82 | B86: 4.販売 | C86: 4.出荷 | D86: 4.16 | E86: B級品管理 | F86: B級品在庫の数量・場所・ステータスを把握できること | G86: 必須 | I86: 標準 | J86: 返却されたB級品については、入庫時に「保留在庫」などのステータスを割り当て、ロット番号で個体識別を行うことにより、その状態や所在を正確に管理・追跡することが可能です。 | K86: - | M86: A | N86: 北勝
A87: 83 | B87: 4.販売 | C87: 4.出荷 | D87: 4.16 | E87: B級品管理 | F87: B級品に対して代替品との交換が可能であり、トレーサビリティを確保できること | G87: 必須 | I87: 標準 | J87: ロット番号で個体識別を行うことにより、その状態や所在を正確に管理・追跡することが可能です。 | K87: - | M87: A | N87: 北勝
A88: 84 | B88: 4.販売 | C88: 5.輸出 | D88: 5.4 | E88: 輸出関連帳票発行 | F88: Invoice を修正可能な帳票として出力できること | G88: 必須 | H88: 〇 | I88: アドオン・カスタマイズ | J88: 修正可能な帳票として出力する機能は標準では具備していないため、帳票をExcel出力するアドオン開発が必要です。 | K88: 800000 | L88: 回答のニュアンスあっているか？ | N88: 北勝 | O88: Invoice
A89: 85 | B89: 4.販売 | C89: 5.輸出 | D89: 5.4 | E89: 輸出関連帳票発行 | F89: PackingList を修正可能な帳票として出力できること | G89: 必須 | H89: 〇 | I89: アドオン・カスタマイズ | J89: PackingList出力機能標準では具備していないため、アドオン開発が必要です。 | K89: 800000 | L89: 回答のニュアンスあっているか？ | N89: 北勝 | O89: PackingList
A90: 86 | B90: 4.販売 | C90: 5.輸出 | D90: 5.7 | E90: CaseMark発行 | F90: CaseMark を修正可能な帳票として出力できること | G90: 必須 | H90: 〇 | I90: アドオン・カスタマイズ | J90: 輸送梱包に貼付する「ケースマーク（荷印）」については、SAPの標準フォームテンプレートとして独立したものは具備していないため、アドオン開発が必要です。 | K90: 800000 | L90: 回答のニュアンスあっているか？ | N90: 北勝 | O90: CaseMark
A91: 87 | B91: 4.販売 | C91: 5.輸出 | D91: 5.4 | E91: 輸出関連帳票発行 | F91: 輸出帳票において品目などを英語表記で出力できること | G91: 必須 | I91: 標準 | J91: 品目テキストや帳票ラベルを英語に動的に切り替えて発行する機能を具備しております。 | K91: - | M91: A | N91: 北勝
A92: 88 | B92: 4.販売 | C92: 5.輸出 | D92: 5.4 | E92: 輸出関連帳票発行 | F92: 得意先別品目名を登録できること | G92: 必須 | I92: 標準 | J92: 得意先品目管理機能を具備しております。 | K92: - | M92: A | N92: 北勝
A93: 89 | B93: 4.販売 | C93: 5.輸出 | D93: 5.1 | E93: 輸出申請書類への転用 | F93: インボイスデータを出力し、仲介貿易申請書および輸出等申請書に転用できること | G93: 任意 | I93: アドオン・カスタマイズ | J93: 仲介貿易申請書や輸出等申請書といった日本固有の申請書類を出力する機能は具備していないため、アドオン開発が必要です。 | K93: 1600000 | N93: 北勝 | O93: 仲介貿易申請書 輸出等申請書
A94: 90 | B94: 4.販売 | C94: 5.輸出 | D94: 5.4 | E94: 輸出関連帳票発行 | F94: 3国間取引における輸入者へ直送ができること | G94: 必須 | H94: 〇 | I94: 標準 | J94: 基本的な3国間取引の管理機能を具備しております。 | K94: - | M94: A | N94: 北勝
A95: 91 | B95: 4.販売 | C95: 5.輸出 | D95: 5.4 | E95: 輸出関連帳票発行 | F95: 出荷時には Shipping Invoice および Commercial Invoice を出力する。 | G95: 必須 | H95: 〇 | I95: 標準 | J95: Shipping Invoiceは出荷伝票（Delivery Note）として出荷伝票の作成時、またはピッキング・出庫確認のタイミングで出力する機能を具備しております。 Commercial Invoiceは請求伝票（Billing Document）として出荷に基づく請求伝票の作成時に出力する機能を具備しております。。 | K95: - | M95: B | N95: 北勝
A96: 92 | B96: 4.販売 | C96: 5.輸出 | D96: ー | E96: 輸出関連帳票発行 | F96: 返品時に Credit Note を出力できること | G96: 必須 | H96: 〇 | I96: 標準 | J96: クレジットメモ発行機能を具備しております。 | K96: - | M96: A | N96: 北勝
A97: 93 | B97: 4.販売 | C97: 5.輸出 | D97: ー | E97: 輸出関連帳票発行 | F97: 売上以外の請求が必要な場合に Debit Note を出力できること | G97: 必須 | H97: 〇 | I97: 標準 | J97: デビットメモ発行機能を具備しております。 | K97: - | M97: A | N97: 北勝
A98: 94 | B98: 4.販売 | C98: 5.輸出 | D98: ー | E98: 輸出関連帳票発行 | F98: 在庫品以外の Invoice を出力できること | G98: 必須 | H98: 〇 | I98: 標準 | J98: 在庫品・非在庫品を問わずInvoiceを出力する標準を具備しております。 | K98: - | M98: A | N98: 北勝
A99: 95 | B99: 4.販売 | C99: 6.移動 | D99: 6.1 | E99: 移動指示登録 | F99: 移動指示の登録から移動指示書の出力および在庫移動入力までをシステム上で一連の処理として実施できること | G99: 必須 | I99: 標準 | J99: 標準の倉庫管理機能により、移動指示の登録から指示書出力、在庫移動転記までの一連のプロセスを統合的に処理する機能を具備しております。 | K99: - | L99: おそらくASの出荷即売上の制約により、工事案件では一度在庫移動する必要があった。SAPではEPPMを用いて完成基準となるため、在庫移動自体不要になりそう。 | M99: A | N99: 北勝
A100: 96 | B100: 4.販売 | C100: 6.移動 | D100: 6.1 | E100: 移動指示登録 | F100: 移動指示伝票およびExcel依頼カードで代替している各種依頼（在庫改造依頼、滞留品検査、貸出処理）をシステム上で登録および管理できること | G100: 必須 | I100: 標準 | J100: 移動指示伝票、滞留品検査、貸出処理について標準機能を具備しております。 一度完成して在庫計上された製品に対して、追加の加工や修正が必要になった際のプロセスに対応しております。 | K100: - | L100: 貸出：1IU 改造：BJN (改造依頼の定義) おそらくASの出荷即売上の制約により、工事案件では一度在庫移動する必要があった。SAPではEPPMを用いて完成基準となるため、在庫移動自体不要になりそう。 | M100: A | N100: 北勝
A101: 97 | B101: 4.販売 | C101: 6.移動 | D101: 6.5 | E101: 営業へ移動連絡 | F101: 在庫移動入力をもって移動完了とし、出荷日、納品日、送付先、送り状番号などの移動完了情報をシステム上で確認できること | G101: 必須 | I101: 標準 | J101: 在庫移動（入出庫確認）の入力を行うことで、そのステータスが「完了」となり、関連する日付や配送情報を伝票単位で一元管理する機能を具備しております。 | K101: - | L101: おそらくASの出荷即売上の制約により、工事案件では一度在庫移動する必要があった。SAPではEPPMを用いて完成基準となるため、在庫移動自体不要になりそう。 | M101: A | N101: 北勝
A102: 98 | B102: 4.販売 | C102: 6.移動 | D102: 6.5 | E102: 営業へ移動連絡 | F102: 在庫移動入力完了時に指定宛先へ完了通知メールを自動配信できること | G102: 必須 | I102: 標準 | J102: 在庫移動をトリガーとして、あらかじめ設定した宛先に対し、電子メールを自動的に送信する仕組みが備わっています。 | K102: - | L102: 指定宛先の動的決定ロジックには制限がある おそらくASの出荷即売上の制約により、工事案件では一度在庫移動する必要があった。SAPではEPPMを用いて完成基準となるため、在庫移動自体不要になりそう。 | M102: A | N102: 北勝
...

Sheet (参考)現行システム機能階層一覧
A1: No. | B1: 業務分類 | E1: 機能ID | F1: 機能名 | G1: 機能概要 | H1: 入力情報 | I1: 出力情報 | J1: 区分 | O1: 備考 | P1: 稼働状況 | Q1: step数 | R1: JCM | AB1: JCMシステムズ | AC1: メイホウ | AE1: スクショ採取
B2: 大分類 | C2: 中分類 | D2: 小分類 | J2: 画面 | K2: クエリ | L2: バッチ | M2: 帳表 | N2: CSV | R2: 情シス | S2: 経理 | T2: 営業 | U2: 人事 | V2: 総務 | W2: コンポーネント | X2: 生産技術 | Y2: 生産 | Z2: アジア営業 | AA2: 購買 | AD2: PG名 | AL2: JS機能 | AO2: 経理 | AS2: 人事
A3: 1 | B3: 販売システム | C3: マスター保守 | D3: ー | E3: SA0050 | F3: 与信マスター | J3: 〇 | Q3: =VLOOKUP(E3,sheet1!$B$2:$D$3209,3,FALSE) -> 1808 | R3: 〇 | S3: 〇 | T3: 〇 | U3: 〇 | V3: 〇 | AB3: 〇 | AC3: 〇 | AD3: =VLOOKUP(E3,sheet1!$B$2:$C$3209,2,FALSE) -> 与信マスターメンテナンス | AE3: 〇 | AF3: 01.与信マスター | AG3: SA0050 | AH3: =MID(AF3,4,100) -> 与信マスター | AO3: =TRIM(MIDB(AQ3,4,99)) -> 与信マスター | AP3: =TRIM(AR3) -> SA0050 | AQ3: 01.与信マスター | AR3: SA0050 | AS3: =TRIM(MID(AU3,4,99)) -> 与信マスター | AT3: =TRIM(AV3) -> SA0050 | AU3: 01.与信マスター | AV3: SA0050
A4: 2 | B4: 販売システム | C4: マスター保守 | D4: ー | E4: SA0060 | F4: 販売価格マスター | J4: 〇 | Q4: =VLOOKUP(E4,sheet1!$B$2:$D$3209,3,FALSE) -> 1222 | R4: 〇 | S4: 〇 | T4: 〇 | U4: 〇 | V4: 〇 | Z4: 〇 | AB4: 〇 | AC4: 〇 | AD4: =VLOOKUP(E4,sheet1!$B$2:$C$3209,2,FALSE) -> 販売価格マスターメンテナンス | AE4: 〇 | AF4: 02.販売価格マスター | AG4: SA0060 | AH4: =MID(AF4,4,100) -> 販売価格マスター | AO4: =TRIM(MIDB(AQ4,4,99)) -> 販売価格マスター | AP4: =TRIM(AR4) -> SA0060 | AQ4: 02.販売価格マスター | AR4: SA0060 | AS4: =TRIM(MID(AU4,4,99)) -> 販売価格マスター | AT4: =TRIM(AV4) -> SA0060 | AU4: 02.販売価格マスター | AV4: SA0060
A5: 3 | B5: 販売システム | C5: マスター保守 | D5: ー | E5: SA0120 | F5: 値引限度率マスター | J5: 〇 | Q5: =VLOOKUP(E5,sheet1!$B$2:$D$3209,3,FALSE) -> 872 | R5: 〇 | S5: 〇 | T5: 〇 | U5: 〇 | V5: 〇 | AB5: 〇 | AC5: 〇 | AD5: =VLOOKUP(E5,sheet1!$B$2:$C$3209,2,FALSE) -> 値引限度額・率マスターメンテナンス | AF5: 03.値引限度率マスター | AG5: SA0120 | AH5: =MID(AF5,4,100) -> 値引限度率マスター | AO5: =TRIM(MIDB(AQ5,4,99)) -> 値引限度率マスター | AP5: =TRIM(AR5) -> SA0120 | AQ5: 03.値引限度率マスター | AR5: SA0120 | AS5: =TRIM(MID(AU5,4,99)) -> 値引限度率マスター | AT5: =TRIM(AV5) -> SA0120 | AU5: 03.値引限度率マスター | AV5: SA0120
A6: 4 | B6: 販売システム | C6: マスター保守 | D6: ー | E6: SA0080 | F6: 修理作業費マスター | J6: 〇 | Q6: =VLOOKUP(E6,sheet1!$B$2:$D$3209,3,FALSE) -> 471 | R6: 〇 | S6: 〇 | T6: 〇 | U6: 〇 | V6: 〇 | AB6: 〇 | AC6: 〇 | AD6: =VLOOKUP(E6,sheet1!$B$2:$C$3209,2,FALSE) -> 修理作業費マスターメンテ | AF6: 04.修理作業費マスター | AG6: SA0080 | AH6: =MID(AF6,4,100) -> 修理作業費マスター | AO6: =TRIM(MIDB(AQ6,4,99)) -> 修理作業費マスター | AP6: =TRIM(AR6) -> SA0080 | AQ6: 04.修理作業費マスター | AR6: SA0080 | AS6: =TRIM(MID(AU6,4,99)) -> 修理作業費マスター | AT6: =TRIM(AV6) -> SA0080 | AU6: 04.修理作業費マスター | AV6: SA0080
A7: 5 | B7: 販売システム | C7: マスター保守 | D7: ー | E7: SA0210 | F7: 無償保証期間マスターメンテ | J7: 〇 | Q7: =VLOOKUP(E7,sheet1!$B$2:$D$3209,3,FALSE) -> 631 | R7: 〇 | S7: 〇 | T7: 〇 | U7: 〇 | V7: 〇 | AB7: 〇 | AC7: 〇 | AD7: =VLOOKUP(E7,sheet1!$B$2:$C$3209,2,FALSE) -> 無償保証期間マスターメンテ | AF7: 05.無償保証期間マスターメンテ | AG7: SA0210 | AH7: =MID(AF7,4,100) -> 無償保証期間マスターメンテ | AO7: =TRIM(MIDB(AQ7,4,99)) -> 無償保証期間マスターメンテ | AP7: =TRIM(AR7) -> SA0210 | AQ7: 05.無償保証期間マスターメンテ | AR7: SA0210 | AS7: =TRIM(MID(AU7,4,99)) -> 無償保証期間マスターメンテ | AT7: =TRIM(AV7) -> SA0210 | AU7: 05.無償保証期間マスターメンテ | AV7: SA0210
A8: 6 | B8: 販売システム | C8: マスター保守 | D8: ー | E8: MM0020 | F8: 銀行マスタメンテナンス | J8: 〇 | Q8: =VLOOKUP(E8,sheet1!$B$2:$D$3209,3,FALSE) -> 391 | R8: 〇 | S8: 〇 | T8: 〇 | U8: 〇 | V8: 〇 | AB8: 〇 | AC8: 〇 | AD8: =VLOOKUP(E8,sheet1!$B$2:$C$3209,2,FALSE) -> 銀行マスタメンテナンス | AF8: 06.銀行マスタメンテナンス | AG8: MM0020 | AH8: =MID(AF8,4,100) -> 銀行マスタメンテナンス | AO8: =TRIM(MIDB(AQ8,4,99)) -> 銀行マスタメンテナンス | AP8: =TRIM(AR8) -> MM0020 | AQ8: 06.銀行マスタメンテナンス | AR8: MM0020 | AS8: =TRIM(MID(AU8,4,99)) -> 銀行マスタメンテナンス | AT8: =TRIM(AV8) -> MM0020 | AU8: 06.銀行マスタメンテナンス | AV8: MM0020
A9: 7 | B9: 販売システム | C9: マスター保守 | D9: ー | E9: SA0220 | F9: 銀行振込口座マスター | J9: 〇 | Q9: =VLOOKUP(E9,sheet1!$B$2:$D$3209,3,FALSE) -> 535 | R9: 〇 | S9: 〇 | T9: 〇 | U9: 〇 | V9: 〇 | AB9: 〇 | AC9: 〇 | AD9: =VLOOKUP(E9,sheet1!$B$2:$C$3209,2,FALSE) -> 銀行振込口座マスターメンテ | AF9: 07.銀行振込口座マスター | AG9: SA0220 | AH9: =MID(AF9,4,100) -> 銀行振込口座マスター | AO9: =TRIM(MIDB(AQ9,4,99)) -> 銀行振込口座マスター | AP9: =TRIM(AR9) -> SA0220 | AQ9: 07.銀行振込口座マスター | AR9: SA0220 | AS9: =TRIM(MID(AU9,4,99)) -> 銀行振込口座マスター | AT9: =TRIM(AV9) -> SA0220 | AU9: 07.銀行振込口座マスター | AV9: SA0220
A10: 8 | B10: 販売システム | C10: マスター保守 | D10: 与信限度申請書管理 | E10: SA0170 | F10: 与信決裁内容登録 | J10: 〇 | Q10: =VLOOKUP(E10,sheet1!$B$2:$D$3209,3,FALSE) -> 1116 | R10: 〇 | S10: 〇 | T10: 〇 | U10: 〇 | V10: 〇 | AC10: 〇 | AD10: =VLOOKUP(E10,sheet1!$B$2:$C$3209,2,FALSE) -> 与信決裁内容登録 | AE10: 〇 | AF10: 01.与信決裁内容登録 | AG10: SA0170 | AH10: =MID(AF10,4,100) -> 与信決裁内容登録 | AO10: =TRIM(MIDB(AQ10,4,99)) -> 与信決裁内容登録 | AP10: =TRIM(AR10) -> SA0170 | AQ10: 01.与信決裁内容登録 | AR10: SA0170 | AS10: =TRIM(MID(AU10,4,99)) -> 与信決裁内容登録 | AT10: =TRIM(AV10) -> SA0170 | AU10: 01.与信決裁内容登録 | AV10: SA0170
A11: 9 | B11: 販売システム | C11: マスター保守 | D11: 与信限度申請書管理 | E11: SA2435 | F11: 月末与信残高集計 更新系 | J11: 〇 | Q11: =VLOOKUP(E11,sheet1!$B$2:$D$3209,3,FALSE) -> 210 | R11: 〇 | S11: 〇 | T11: 〇 | U11: 〇 | V11: 〇 | AC11: 〇 | AD11: =VLOOKUP(E11,sheet1!$B$2:$C$3209,2,FALSE) -> 月末与信残高集計指示画面 | AE11: 〇 | AF11: 11.月末与信残高集計 更新系 | AG11: SA2435 | AH11: =MID(AF11,4,100) -> 月末与信残高集計 更新系 | AO11: =TRIM(MIDB(AQ11,4,99)) -> 月末与信残高集計 更新系 | AP11: =TRIM(AR11) -> SA2435 | AQ11: 11.月末与信残高集計 更新系 | AR11: SA2435 | AS11: =TRIM(MID(AU11,4,99)) -> 月末与信残高集計 更新系 | AT11: =TRIM(AV11) -> SA2435 | AU11: 11.月末与信残高集計 更新系 | AV11: SA2435
A12: 10 | B12: 販売システム | C12: マスター保守 | D12: 与信限度申請書管理 | E12: SA0280 | F12: 与信再更新対象データ作成 | J12: 〇 | Q12: =VLOOKUP(E12,sheet1!$B$2:$D$3209,3,FALSE) -> 408 | R12: 〇 | S12: 〇 | T12: 〇 | U12: 〇 | V12: 〇 | AC12: 〇 | AD12: =VLOOKUP(E12,sheet1!$B$2:$C$3209,2,FALSE) -> 与信再更新対象データ作成 | AF12: 12.与信再更新対象データ作成 | AG12: SA0280 | AH12: =MID(AF12,4,100) -> 与信再更新対象データ作成 | AO12: =TRIM(MIDB(AQ12,4,99)) -> 与信再更新対象データ作成 | AP12: =TRIM(AR12) -> SA0280 | AQ12: 12.与信再更新対象データ作成 | AR12: SA0280 | AS12: =TRIM(MID(AU12,4,99)) -> 与信再更新対象データ作成 | AT12: =TRIM(AV12) -> SA0280 | AU12: 12.与信再更新対象データ作成 | AV12: SA0280
A13: 11 | B13: 販売システム | C13: マスター保守 | D13: 与信限度申請書管理 | E13: SA0180 | F13: 外部評価登録 | J13: 〇 | Q13: =VLOOKUP(E13,sheet1!$B$2:$D$3209,3,FALSE) -> 528 | R13: 〇 | S13: 〇 | T13: 〇 | U13: 〇 | V13: 〇 | AC13: 〇 | AD13: =VLOOKUP(E13,sheet1!$B$2:$C$3209,2,FALSE) -> 外部評価登録 | AF13: 13.外部評価登録 | AG13: SA0180 | AH13: =MID(AF13,4,100) -> 外部評価登録 | AO13: =TRIM(MIDB(AQ13,4,99)) -> 外部評価登録 | AP13: =TRIM(AR13) -> SA0180 | AQ13: 13.外部評価登録 | AR13: SA0180 | AS13: =TRIM(MID(AU13,4,99)) -> 外部評価登録 | AT13: =TRIM(AV13) -> SA0180 | AU13: 13.外部評価登録 | AV13: SA0180
A14: 12 | B14: 販売システム | C14: マスター保守 | D14: 与信限度申請書管理 | E14: SA2440 | F14: 与信再更新申請書印刷 | J14: 〇 | Q14: =VLOOKUP(E14,sheet1!$B$2:$D$3209,3,FALSE) -> 513 | R14: 〇 | S14: 〇 | T14: 〇 | U14: 〇 | V14: 〇 | AC14: 〇 | AD14: =VLOOKUP(E14,sheet1!$B$2:$C$3209,2,FALSE) -> 与信限度額申請客先リスト印刷 | AF14: 14.与信再更新申請書印刷 | AG14: SA2440 | AH14: =MID(AF14,4,100) -> 与信再更新申請書印刷 | AO14: =TRIM(MIDB(AQ14,4,99)) -> 与信再更新申請書印刷 | AP14: =TRIM(AR14) -> SA2440 | AQ14: 14.与信再更新申請書印刷 | AR14: SA2440 | AS14: =TRIM(MID(AU14,4,99)) -> 与信再更新申請書印刷 | AT14: =TRIM(AV14) -> SA2440 | AU14: 14.与信再更新申請書印刷 | AV14: SA2440
A15: 13 | B15: 販売システム | C15: マスター保守 | D15: 与信限度申請書管理 | E15: SA0200 | F15: 与信再更新処理 | J15: 〇 | Q15: =VLOOKUP(E15,sheet1!$B$2:$D$3209,3,FALSE) -> 819 | R15: 〇 | S15: 〇 | T15: 〇 | U15: 〇 | V15: 〇 | AC15: 〇 | AD15: =VLOOKUP(E15,sheet1!$B$2:$C$3209,2,FALSE) -> 与信再申請更新 | AF15: 15.与信再更新処理 | AG15: SA0200 | AH15: =MID(AF15,4,100) -> 与信再更新処理 | AO15: =TRIM(MIDB(AQ15,4,99)) -> 与信再更新処理 | AP15: =TRIM(AR15) -> SA0200 | AQ15: 15.与信再更新処理 | AR15: SA0200 | AS15: =TRIM(MID(AU15,4,99)) -> 与信再更新処理 | AT15: =TRIM(AV15) -> SA0200 | AU15: 15.与信再更新処理 | AV15: SA0200
A16: 14 | B16: 販売システム | C16: マスター保守 | D16: 与信限度申請書管理 | E16: SA0190 | F16: 期間限定与信限度額登録 | J16: 〇 | Q16: =VLOOKUP(E16,sheet1!$B$2:$D$3209,3,FALSE) -> 351 | R16: 〇 | S16: 〇 | T16: 〇 | U16: 〇 | V16: 〇 | AC16: 〇 | AD16: =VLOOKUP(E16,sheet1!$B$2:$C$3209,2,FALSE) -> 期間限定与信限度登録 | AF16: 21.期間限定与信限度額登録 | AG16: SA0190 | AH16: =MID(AF16,4,100) -> 期間限定与信限度額登録 | AO16: =TRIM(MIDB(AQ16,4,99)) -> 期間限定与信限度額登録 | AP16: =TRIM(AR16) -> SA0190 | AQ16: 21.期間限定与信限度額登録 | AR16: SA0190 | AS16: =TRIM(MID(AU16,4,99)) -> 期間限定与信限度額登録 | AT16: =TRIM(AV16) -> SA0190 | AU16: 21.期間限定与信限度額登録 | AV16: SA0190
A17: 15 | B17: 販売システム | C17: マスター保守 | D17: 与信限度申請書管理 | E17: SA2450 | F17: 期間限定与信登録中客先印刷 | J17: 〇 | Q17: =VLOOKUP(E17,sheet1!$B$2:$D$3209,3,FALSE) -> 327 | R17: 〇 | S17: 〇 | T17: 〇 | U17: 〇 | V17: 〇 | AC17: 〇 | AD17: =VLOOKUP(E17,sheet1!$B$2:$C$3209,2,FALSE) -> 期間限定与信限度客先印刷 | AF17: 22.期間限定与信登録中客先印刷 | AG17: SA2450 | AH17: =MID(AF17,4,100) -> 期間限定与信登録中客先印刷 | AO17: =TRIM(MIDB(AQ17,4,99)) -> 期間限定与信登録中客先印刷 | AP17: =TRIM(AR17) -> SA2450 | AQ17: 22.期間限定与信登録中客先印刷 | AR17: SA2450 | AS17: =TRIM(MID(AU17,4,99)) -> 期間限定与信登録中客先印刷 | AT17: =TRIM(AV17) -> SA2450 | AU17: 22.期間限定与信登録中客先印刷 | AV17: SA2450
A18: 16 | B18: 販売システム | C18: マスター保守 | D18: 与信限度申請書管理 | E18: SA5180 | F18: 与信申請データ照会 | J18: 〇 | Q18: =VLOOKUP(E18,sheet1!$B$2:$D$3209,3,FALSE) -> 576 | R18: 〇 | S18: 〇 | T18: 〇 | U18: 〇 | V18: 〇 | AC18: 〇 | AD18: =VLOOKUP(E18,sheet1!$B$2:$C$3209,2,FALSE) -> 与信決裁内容照会 | AF18: 51.与信申請データ照会 | AG18: SA5180 | AH18: =MID(AF18,4,100) -> 与信申請データ照会 | AO18: =TRIM(MIDB(AQ18,4,99)) -> 与信申請データ照会 | AP18: =TRIM(AR18) -> SA5180 | AQ18: 51.与信申請データ照会 | AR18: SA5180 | AS18: =TRIM(MID(AU18,4,99)) -> 与信申請データ照会 | AT18: =TRIM(AV18) -> SA5180 | AU18: 51.与信申請データ照会 | AV18: SA5180
A19: 17 | B19: 販売システム | C19: マスター保守 | D19: 与信限度申請書管理 | E19: Query | F19: 与信再更新申請書データ抽出 | K19: 〇 | N19: 〇 | Q19: =VLOOKUP(E19,sheet1!$B$2:$D$3209,3,FALSE) -> #N/A | R19: 〇 | S19: 〇 | T19: 〇 | U19: 〇 | V19: 〇 | AC19: 〇 | AD19: =VLOOKUP(E19,sheet1!$B$2:$C$3209,2,FALSE) -> #N/A | AF19: 61.与信再更新申請書データ抽出 | AG19: Query | AH19: =MID(AF19,4,100) -> 与信再更新申請書データ抽出 | AO19: =TRIM(MIDB(AQ19,4,99)) -> 与信再更新申請書データ抽出 | AP19: =TRIM(AR19) -> Query | AQ19: 61.与信再更新申請書データ抽出 | AR19: Query | AS19: =TRIM(MID(AU19,4,99)) -> 与信再更新申請書データ抽出 | AT19: =TRIM(AV19) -> Query | AU19: 61.与信再更新申請書データ抽出 | AV19: Query
A20: 18 | B20: 販売システム | C20: マスター保守 | D20: 与信限度申請書管理 | E20: Query | F20: 与信決裁内容ＤＬ 日付指定JCM | K20: 〇 | N20: 〇 | Q20: =VLOOKUP(E20,sheet1!$B$2:$D$3209,3,FALSE) -> #N/A | R20: 〇 | S20: 〇 | T20: 〇 | U20: 〇 | V20: 〇 | AC20: 〇 | AD20: =VLOOKUP(E20,sheet1!$B$2:$C$3209,2,FALSE) -> #N/A | AF20: 62 与信決裁内容ＤＬ 日付指定JCM | AG20: Query | AH20: =MID(AF20,4,100) -> 与信決裁内容ＤＬ 日付指定JCM | AO20: =TRIM(MIDB(AQ20,4,99)) -> 与信決裁内容ＤＬ 日付指定JCM | AP20: =TRIM(AR20) -> Query | AQ20: 62 与信決裁内容ＤＬ 日付指定JCM | AR20: Query | AS20: =TRIM(MID(AU20,4,99)) -> 与信決裁内容ＤＬ 日付指定JCM | AT20: =TRIM(AV20) -> Query | AU20: 62 与信決裁内容ＤＬ 日付指定JCM | AV20: Query
A21: 19 | B21: 販売システム | C21: マスター保守 | D21: 与信限度申請書管理 | E21: Query | F21: 与信決裁内容ＤＬ 日付指定JS | K21: 〇 | N21: 〇 | Q21: =VLOOKUP(E21,sheet1!$B$2:$D$3209,3,FALSE) -> #N/A | R21: 〇 | S21: 〇 | T21: 〇 | U21: 〇 | V21: 〇 | AC21: 〇 | AD21: =VLOOKUP(E21,sheet1!$B$2:$C$3209,2,FALSE) -> #N/A | AF21: 63 与信決裁内容ＤＬ 日付指定JS | AG21: Query | AH21: =MID(AF21,4,100) -> 与信決裁内容ＤＬ 日付指定JS | AO21: =TRIM(MIDB(AQ21,4,99)) -> 与信決裁内容ＤＬ 日付指定JS | AP21: =TRIM(AR21) -> Query | AQ21: 63 与信決裁内容ＤＬ 日付指定JS | AR21: Query | AS21: =TRIM(MID(AU21,4,99)) -> 与信決裁内容ＤＬ 日付指定JS | AT21: =TRIM(AV21) -> Query | AU21: 63 与信決裁内容ＤＬ 日付指定JS | AV21: Query
A22: 20 | B22: 販売システム | C22: マスター保守 | D22: ー | E22: PD0132 | F22: 得意先マスタ保守 | J22: 〇 | Q22: =VLOOKUP(E22,sheet1!$B$2:$D$3209,3,FALSE) -> 1485 | R22: 〇 | S22: 〇 | T22: 〇 | U22: 〇 | V22: 〇 | AC22: 〇 | AD22: =VLOOKUP(E22,sheet1!$B$2:$C$3209,2,FALSE) -> 得意先マスターメンテナンス | AF22: 11.得意先マスタ保守 | AG22: PD0132 | AH22: =MID(AF22,4,100) -> 得意先マスタ保守 | AO22: =TRIM(MIDB(AQ22,4,99)) -> 得意先マスタ保守 | AP22: =TRIM(AR22) -> PD0132 | AQ22: 11.得意先マスタ保守 | AR22: PD0132 | AS22: =TRIM(MID(AU22,4,99)) -> 得意先マスタ保守 | AT22: =TRIM(AV22) -> PD0132 | AU22: 11.得意先マスタ保守 | AV22: PD0132
A23: 21 | B23: 販売システム | C23: マスター保守 | D23: ー | E23: SA0070 | F23: 品目・販売課関連ﾏｽﾀｰ | J23: 〇 | Q23: =VLOOKUP(E23,sheet1!$B$2:$D$3209,3,FALSE) -> 688 | R23: 〇 | T23: 〇 | V23: 〇 | AB23: 〇 | AC23: 〇 | AD23: =VLOOKUP(E23,sheet1!$B$2:$C$3209,2,FALSE) -> 品目・販売課関連マスターメンテナンス | AF23: 21.品目・販売課関連ﾏｽﾀｰ | AG23: SA0070 | AH23: =MID(AF23,4,100) -> 品目・販売課関連ﾏｽﾀｰ | AO23: =TRIM(MIDB(AQ23,4,99)) | AP23: =TRIM(AR23) | AS23: =TRIM(MID(AU23,4,99)) | AT23: =TRIM(AV23)
A24: 22 | B24: 販売システム | C24: マスター保守 | D24: ー | E24: SA0090 | F24: ｼﾘｱﾙ NO付加情報ﾏｽﾀｰ | J24: 〇 | Q24: =VLOOKUP(E24,sheet1!$B$2:$D$3209,3,FALSE) -> 673 | R24: 〇 | T24: 〇 | V24: 〇 | AB24: 〇 | AC24: 〇 | AD24: =VLOOKUP(E24,sheet1!$B$2:$C$3209,2,FALSE) -> シリアルＮＯ付加情報マスターメンテナンス | AF24: 22.ｼﾘｱﾙ NO付加情報ﾏｽﾀｰ | AG24: SA0090 | AH24: =MID(AF24,4,100) -> ｼﾘｱﾙ NO付加情報ﾏｽﾀｰ | AO24: =TRIM(MIDB(AQ24,4,99)) | AP24: =TRIM(AR24) | AS24: =TRIM(MID(AU24,4,99)) | AT24: =TRIM(AV24)
A25: 23 | B25: 販売システム | C25: マスター保守 | D25: ー | E25: SA0110 | F25: 荷姿マスター | J25: 〇 | Q25: =VLOOKUP(E25,sheet1!$B$2:$D$3209,3,FALSE) -> 666 | R25: 〇 | T25: 〇 | V25: 〇 | AB25: 〇 | AC25: 〇 | AD25: =VLOOKUP(E25,sheet1!$B$2:$C$3209,2,FALSE) -> 荷姿マスターメンテナンス | AF25: 23.荷姿マスター | AG25: SA0110 | AH25: =MID(AF25,4,100) -> 荷姿マスター | AO25: =TRIM(MIDB(AQ25,4,99)) | AP25: =TRIM(AR25) | AS25: =TRIM(MID(AU25,4,99)) | AT25: =TRIM(AV25)
A26: 24 | B26: 販売システム | C26: マスター保守 | D26: ー | E26: SA0140 | F26: 自動引当可能課マスター | J26: 〇 | Q26: =VLOOKUP(E26,sheet1!$B$2:$D$3209,3,FALSE) -> 613 | R26: 〇 | T26: 〇 | V26: 〇 | AB26: 〇 | AC26: 〇 | AD26: =VLOOKUP(E26,sheet1!$B$2:$C$3209,2,FALSE) -> 自動引当可能課マスターメンテナンス | AF26: 24.自動引当可能課マスター | AG26: SA0140 | AH26: =MID(AF26,4,100) -> 自動引当可能課マスター | AO26: =TRIM(MIDB(AQ26,4,99)) | AP26: =TRIM(AR26) | AS26: =TRIM(MID(AU26,4,99)) | AT26: =TRIM(AV26)
A27: 25 | B27: 販売システム | C27: マスター保守 | D27: ー | E27: SA0010 | F27: 不具合内容マスター | J27: 〇 | Q27: =VLOOKUP(E27,sheet1!$B$2:$D$3209,3,FALSE) -> 243 | R27: 〇 | S27: 〇 | T27: 〇 | U27: 〇 | V27: 〇 | AB27: 〇 | AC27: 〇 | AD27: =VLOOKUP(E27,sheet1!$B$2:$C$3209,2,FALSE) -> 不具合内容マスターメンテ | AF27: 51.不具合内容マスター | AG27: SA0010 | AH27: =MID(AF27,4,100) -> 不具合内容マスター | AO27: =TRIM(MIDB(AQ27,4,99)) -> 不具合内容マスター | AP27: =TRIM(AR27) -> SA0010 | AQ27: 51.不具合内容マスター | AR27: SA0010 | AS27: =TRIM(MID(AU27,4,99)) -> 不具合内容マスター | AT27: =TRIM(AV27) -> SA0010 | AU27: 51.不具合内容マスター | AV27: SA0010
A28: 26 | B28: 販売システム | C28: マスター保守 | D28: ー | E28: SA0020 | F28: 不具合原因マスター | J28: 〇 | Q28: =VLOOKUP(E28,sheet1!$B$2:$D$3209,3,FALSE) -> 242 | R28: 〇 | S28: 〇 | T28: 〇 | U28: 〇 | V28: 〇 | AB28: 〇 | AC28: 〇 | AD28: =VLOOKUP(E28,sheet1!$B$2:$C$3209,2,FALSE) -> 不具合原因マスターメンテ | AF28: 52.不具合原因マスター | AG28: SA0020 | AH28: =MID(AF28,4,100) -> 不具合原因マスター | AO28: =TRIM(MIDB(AQ28,4,99)) -> 不具合原因マスター | AP28: =TRIM(AR28) -> SA0020 | AQ28: 52.不具合原因マスター | AR28: SA0020 | AS28: =TRIM(MID(AU28,4,99)) -> 不具合原因マスター | AT28: =TRIM(AV28) -> SA0020 | AU28: 52.不具合原因マスター | AV28: SA0020
A29: 27 | B29: 販売システム | C29: マスター保守 | D29: ー | E29: SA0030 | F29: 処置内容マスター | J29: 〇 | Q29: =VLOOKUP(E29,sheet1!$B$2:$D$3209,3,FALSE) -> 243 | R29: 〇 | S29: 〇 | T29: 〇 | U29: 〇 | V29: 〇 | AB29: 〇 | AC29: 〇 | AD29: =VLOOKUP(E29,sheet1!$B$2:$C$3209,2,FALSE) -> 処置内容マスターメンテ | AF29: 53.処置内容マスター | AG29: SA0030 | AH29: =MID(AF29,4,100) -> 処置内容マスター | AO29: =TRIM(MIDB(AQ29,4,99)) -> 処置内容マスター | AP29: =TRIM(AR29) -> SA0030 | AQ29: 53.処置内容マスター | AR29: SA0030 | AS29: =TRIM(MID(AU29,4,99)) -> 処置内容マスター | AT29: =TRIM(AV29) -> SA0030 | AU29: 53.処置内容マスター | AV29: SA0030
A30: 28 | B30: 販売システム | C30: マスター保守 | D30: ー | E30: SA0100 | F30: 保守契約マスター | J30: 〇 | Q30: =VLOOKUP(E30,sheet1!$B$2:$D$3209,3,FALSE) -> 1867 | R30: 〇 | S30: 〇 | T30: 〇 | U30: 〇 | V30: 〇 | AB30: 〇 | AC30: 〇 | AD30: =VLOOKUP(E30,sheet1!$B$2:$C$3209,2,FALSE) -> 保守契約マスターメンテ | AF30: 54.保守契約マスター | AG30: SA0100 | AH30: =MID(AF30,4,100) -> 保守契約マスター | AO30: =TRIM(MIDB(AQ30,4,99)) -> 保守契約マスター | AP30: =TRIM(AR30) -> SA0030 | AQ30: 54.保守契約マスター | AR30: SA0030 | AS30: =TRIM(MID(AU30,4,99)) -> 保守契約マスター | AT30: =TRIM(AV30) -> SA0030 | AU30: 54.保守契約マスター | AV30: SA0030
A31: 29 | B31: 販売システム | C31: マスター保守 | D31: ー | E31: AC0032 | F31: ｼｽﾃﾑ式・単能式品目F | J31: 〇 | Q31: =VLOOKUP(E31,sheet1!$B$2:$D$3209,3,FALSE) -> 563 | R31: 〇 | S31: 〇 | T31: 〇 | U31: 〇 | V31: 〇 | Z31: 〇 | AB31: 〇 | AC31: 〇 | AD31: =VLOOKUP(E31,sheet1!$B$2:$C$3209,2,FALSE) -> ｼｽﾃﾑ式・単能式品目ﾌｧｲﾙﾒﾝﾃﾅﾝｽ | AF31: 61.ｼｽﾃﾑ式・単能式品目F | AG31: AC0032 | AH31: =MID(AF31,4,100) -> ｼｽﾃﾑ式・単能式品目F | AO31: =TRIM(MIDB(AQ31,4,99)) -> ｼｽﾃﾑ式・単能式品目F | AP31: =TRIM(AR31) -> AC0032 | AQ31: 61. ｼｽﾃﾑ式・単能式品目F | AR31: AC0032 | AS31: =TRIM(MID(AU31,4,99)) -> ｼｽﾃﾑ式・単能式品目F | AT31: =TRIM(AV31) -> AC0032 | AU31: 61. ｼｽﾃﾑ式・単能式品目F | AV31: AC0032
A32: 30 | B32: 販売システム | C32: マスター照会 | D32: ー | E32: SA1540 | F32: 与信マスター・親得意 | J32: 〇 | Q32: =VLOOKUP(E32,sheet1!$B$2:$D$3209,3,FALSE) -> 387 | R32: 〇 | S32: 〇 | T32: 〇 | U32: 〇 | V32: 〇 | Z32: 〇 | AB32: 〇 | AC32: 〇 | AD32: =VLOOKUP(E32,sheet1!$B$2:$C$3209,2,FALSE) -> 与信マスター照会（１） | AF32: 01.与信マスター・親得意 | AG32: SA1540 | AH32: =MID(AF32,4,100) -> 与信マスター・親得意 | AL32: =TRIM(AN32) -> 与信マスター・親得意 | AM32: 〇 | AN32: 与信マスター・親得意 | AO32: =TRIM(MIDB(AQ32,4,99)) -> 与信マスター・親得意 | AP32: =TRIM(AR32) -> SA1540 | AQ32: 01.与信マスター・親得意 | AR32: SA1540 | AS32: =TRIM(MID(AU32,4,99)) -> 与信マスター・親得意 | AT32: =TRIM(AV32) -> SA1540 | AU32: 01.与信マスター・親得意 | AV32: SA1540
A33: 31 | B33: 販売システム | C33: マスター照会 | D33: ー | E33: SA1550 | F33: 与信マスター・得意先 | J33: 〇 | Q33: =VLOOKUP(E33,sheet1!$B$2:$D$3209,3,FALSE) -> 429 | R33: 〇 | S33: 〇 | T33: 〇 | U33: 〇 | V33: 〇 | Z33: 〇 | AB33: 〇 | AC33: 〇 | AD33: =VLOOKUP(E33,sheet1!$B$2:$C$3209,2,FALSE) -> 与信マスター照会（２） | AF33: 02.与信マスター・得意先 | AG33: SA1550 | AH33: =MID(AF33,4,100) -> 与信マスター・得意先 | AL33: =TRIM(AN33) -> 与信マスター・得意先 | AM33: 〇 | AN33: 与信マスター・得意先 | AO33: =TRIM(MIDB(AQ33,4,99)) -> 与信マスター・得意先 | AP33: =TRIM(AR33) -> SA1550 | AQ33: 02.与信マスター・得意先 | AR33: SA1550 | AS33: =TRIM(MID(AU33,4,99)) -> 与信マスター・得意先 | AT33: =TRIM(AV33) -> SA1550 | AU33: 02.与信マスター・得意先 | AV33: SA1550
A34: 32 | B34: 販売システム | C34: マスター照会 | D34: ー | E34: SA1570 | F34: 販売価格マスター | J34: 〇 | Q34: =VLOOKUP(E34,sheet1!$B$2:$D$3209,3,FALSE) -> 500 | R34: 〇 | S34: 〇 | T34: 〇 | U34: 〇 | V34: 〇 | Z34: 〇 | AB34: 〇 | AC34: 〇 | AD34: =VLOOKUP(E34,sheet1!$B$2:$C$3209,2,FALSE) -> 販売価格マスター照会 | AF34: 03.販売価格マスター | AG34: SA1570 | AH34: =MID(AF34,4,100) -> 販売価格マスター | AL34: =TRIM(AN34) -> 販売価格マスター | AM34: 〇 | AN34: 販売価格マスター | AO34: =TRIM(MIDB(AQ34,4,99)) -> 販売価格マスター | AP34: =TRIM(AR34) -> SA1570 | AQ34: 03.販売価格マスター | AR34: SA1570 | AS34: =TRIM(MID(AU34,4,99)) -> 販売価格マスター | AT34: =TRIM(AV34) -> SA1570 | AU34: 03.販売価格マスター | AV34: SA1570
A35: 33 | B35: 販売システム | C35: マスター照会 | D35: ー | E35: SA1630 | F35: 値引限度率マスター | J35: 〇 | Q35: =VLOOKUP(E35,sheet1!$B$2:$D$3209,3,FALSE) -> 340 | R35: 〇 | S35: 〇 | T35: 〇 | U35: 〇 | V35: 〇 | Z35: 〇 | AB35: 〇 | AC35: 〇 | AD35: =VLOOKUP(E35,sheet1!$B$2:$C$3209,2,FALSE) -> 値引限度額・率マスター照会 | AF35: 04.値引限度率マスター | AG35: SA1630 | AH35: =MID(AF35,4,100) -> 値引限度率マスター | AL35: =TRIM(AN35) -> 値引限度率マスター | AM35: 〇 | AN35: 値引限度率マスター | AO35: =TRIM(MIDB(AQ35,4,99)) -> 値引限度率マスター | AP35: =TRIM(AR35) -> SA1630 | AQ35: 04.値引限度率マスター | AR35: SA1630 | AS35: =TRIM(MID(AU35,4,99)) -> 値引限度率マスター | AT35: =TRIM(AV35) -> SA1630 | AU35: 04.値引限度率マスター | AV35: SA1630
A36: 34 | B36: 販売システム | C36: マスター照会 | D36: ー | E36: SA1590 | F36: 修理作業費マスター | J36: 〇 | Q36: =VLOOKUP(E36,sheet1!$B$2:$D$3209,3,FALSE) -> 281 | R36: 〇 | S36: 〇 | T36: 〇 | U36: 〇 | V36: 〇 | Z36: 〇 | AB36: 〇 | AC36: 〇 | AD36: =VLOOKUP(E36,sheet1!$B$2:$C$3209,2,FALSE) -> 修理作業費マスター照会 | AF36: 05.修理作業費マスター | AG36: SA1590 | AH36: =MID(AF36,4,100) -> 修理作業費マスター | AL36: =TRIM(AN36) -> 修理作業費マスター | AM36: 〇 | AN36: 修理作業費マスター | AO36: =TRIM(MIDB(AQ36,4,99)) -> 修理作業費マスター | AP36: =TRIM(AR36) -> SA1590 | AQ36: 05.修理作業費マスター | AR36: SA1590 | AS36: =TRIM(MID(AU36,4,99)) -> 修理作業費マスター | AT36: =TRIM(AV36) -> SA1590 | AU36: 05.修理作業費マスター | AV36: SA1590
A37: 35 | B37: 販売システム | C37: マスター照会 | D37: ー | E37: SA1660 | F37: 販売引当優先順位Ｍ | J37: 〇 | Q37: =VLOOKUP(E37,sheet1!$B$2:$D$3209,3,FALSE) -> 353 | R37: 〇 | S37: 〇 | T37: 〇 | U37: 〇 | V37: 〇 | Z37: 〇 | AB37: 〇 | AC37: 〇 | AD37: =VLOOKUP(E37,sheet1!$B$2:$C$3209,2,FALSE) -> 販売引当優先順位マスター照会 | AF37: 06.販売引当優先順位Ｍ | AG37: SA1660 | AH37: =MID(AF37,4,100) -> 販売引当優先順位Ｍ | AL37: =TRIM(AN37) -> 販売引当優先順位Ｍ | AM37: 〇 | AN37: 販売引当優先順位Ｍ | AO37: =TRIM(MIDB(AQ37,4,99)) -> 販売引当優先順位Ｍ | AP37: =TRIM(AR37) -> SA1660 | AQ37: 06.販売引当優先順位Ｍ | AR37: SA1660 | AS37: =TRIM(MID(AU37,4,99)) -> 販売引当優先順位Ｍ | AT37: =TRIM(AV37) -> SA1660 | AU37: 06.販売引当優先順位Ｍ | AV37: SA1660
A38: 36 | B38: 販売システム | C38: マスター照会 | D38: ー | E38: SA1650 | F38: 自動引当可能課マスター | J38: 〇 | Q38: =VLOOKUP(E38,sheet1!$B$2:$D$3209,3,FALSE) -> 352 | R38: 〇 | S38: 〇 | T38: 〇 | U38: 〇 | V38: 〇 | Z38: 〇 | AB38: 〇 | AC38: 〇 | AD38: =VLOOKUP(E38,sheet1!$B$2:$C$3209,2,FALSE) -> 自動引当可能課マスター照会 | AF38: 07.自動引当可能課マスター | AG38: SA1650 | AH38: =MID(AF38,4,100) -> 自動引当可能課マスター | AL38: =TRIM(AN38) -> 自動引当可能課マスター | AM38: 〇 | AN38: 自動引当可能課マスター | AO38: =TRIM(MIDB(AQ38,4,99)) -> 自動引当可能課マスター | AP38: =TRIM(AR38) -> SA1650 | AQ38: 07.自動引当可能課マスター | AR38: SA1650 | AS38: =TRIM(MID(AU38,4,99)) -> 自動引当可能課マスター | AT38: =TRIM(AV38) -> SA1650 | AU38: 07.自動引当可能課マスター | AV38: SA1650
A39: 37 | B39: 販売システム | C39: マスター照会 | D39: ー | E39: SA1640 | F39: 発送先固有情報マスター | J39: 〇 | Q39: =VLOOKUP(E39,sheet1!$B$2:$D$3209,3,FALSE) -> 308 | R39: 〇 | S39: 〇 | T39: 〇 | U39: 〇 | V39: 〇 | Z39: 〇 | AB39: 〇 | AC39: 〇 | AD39: =VLOOKUP(E39,sheet1!$B$2:$C$3209,2,FALSE) -> 発送先固有情報マスター照会 | AF39: 08.発送先固有情報マスター | AG39: SA1640 | AH39: =MID(AF39,4,100) -> 発送先固有情報マスター | AL39: =TRIM(AN39) -> 発送先固有情報マスター | AM39: 〇 | AN39: 発送先固有情報マスター | AO39: =TRIM(MIDB(AQ39,4,99)) -> 発送先固有情報マスター | AP39: =TRIM(AR39) -> SA1640 | AQ39: 08.発送先固有情報マスター | AR39: SA1640 | AS39: =TRIM(MID(AU39,4,99)) -> 発送先固有情報マスター | AT39: =TRIM(AV39) -> SA1640 | AU39: 08.発送先固有情報マスター | AV39: SA1640
A40: 38 | B40: 販売システム | C40: マスター照会 | D40: ー | E40: SA1620 | F40: 荷姿マスター | J40: 〇 | Q40: =VLOOKUP(E40,sheet1!$B$2:$D$3209,3,FALSE) -> 284 | R40: 〇 | S40: 〇 | T40: 〇 | U40: 〇 | V40: 〇 | Z40: 〇 | AB40: 〇 | AC40: 〇 | AD40: =VLOOKUP(E40,sheet1!$B$2:$C$3209,2,FALSE) -> 荷姿マスター照会 | AF40: 09.荷姿マスター | AG40: SA1620 | AH40: =MID(AF40,4,100) -> 荷姿マスター | AL40: =TRIM(AN40) -> 荷姿マスター | AM40: 〇 | AN40: 荷姿マスター | AO40: =TRIM(MIDB(AQ40,4,99)) -> 荷姿マスター | AP40: =TRIM(AR40) -> SA1620 | AQ40: 09.荷姿マスター | AR40: SA1620 | AS40: =TRIM(MID(AU40,4,99)) -> 荷姿マスター | AT40: =TRIM(AV40) -> SA1620 | AU40: 09.荷姿マスター | AV40: SA1620
A41: 39 | B41: 販売システム | C41: マスター照会 | D41: ー | E41: SA1600 | F41: シリアルＮＯ付加情報Ｍ | J41: 〇 | Q41: =VLOOKUP(E41,sheet1!$B$2:$D$3209,3,FALSE) -> 382 | R41: 〇 | S41: 〇 | T41: 〇 | U41: 〇 | V41: 〇 | Z41: 〇 | AB41: 〇 | AC41: 〇 | AD41: =VLOOKUP(E41,sheet1!$B$2:$C$3209,2,FALSE) -> シリアルＮＯ付加情報マスター照会 | AF41: 10.シリアルＮＯ付加情報Ｍ | AG41: SA1600 | AH41: =MID(AF41,4,100) -> シリアルＮＯ付加情報Ｍ | AL41: =TRIM(AN41) -> シリアルＮＯ付加情報Ｍ | AM41: 〇 | AN41: シリアルＮＯ付加情報Ｍ | AO41: =TRIM(MIDB(AQ41,4,99)) -> シリアルＮＯ付加情報Ｍ | AP41: =TRIM(AR41) -> SA1600 | AQ41: 10.シリアルＮＯ付加情報Ｍ | AR41: SA1600 | AS41: =TRIM(MID(AU41,4,99)) -> シリアルＮＯ付加情報Ｍ | AT41: =TRIM(AV41) -> SA1600 | AU41: 10.シリアルＮＯ付加情報Ｍ | AV41: SA1600
A42: 40 | B42: 販売システム | C42: マスター照会 | D42: ー | E42: SA5080 | F42: 端末名称照会 | J42: 〇 | Q42: =VLOOKUP(E42,sheet1!$B$2:$D$3209,3,FALSE) -> 89 | R42: 〇 | S42: 〇 | T42: 〇 | U42: 〇 | V42: 〇 | Z42: 〇 | AB42: 〇 | AC42: 〇 | AD42: =VLOOKUP(E42,sheet1!$B$2:$C$3209,2,FALSE) -> 端末名称照会 | AF42: 11.端末名称照会 | AG42: SA5080 | AH42: =MID(AF42,4,100) -> 端末名称照会 | AL42: =TRIM(AN42) -> 端末名称照会 | AM42: 〇 | AN42: 端末名称照会 | AO42: =TRIM(MIDB(AQ42,4,99)) -> 端末名称照会 | AP42: =TRIM(AR42) -> SA5080 | AQ42: 11.端末名称照会 | AR42: SA5080 | AS42: =TRIM(MID(AU42,4,99)) -> 端末名称照会 | AT42: =TRIM(AV42) -> SA5080 | AU42: 11.端末名称照会 | AV42: SA5080
A43: 41 | B43: 販売システム | C43: マスター照会 | D43: ー | E43: PD2220 | F43: 得意先マスタ照会 | J43: 〇 | Q43: =VLOOKUP(E43,sheet1!$B$2:$D$3209,3,FALSE) -> 662 | R43: 〇 | S43: 〇 | T43: 〇 | U43: 〇 | V43: 〇 | Z43: 〇 | AB43: 〇 | AC43: 〇 | AD43: =VLOOKUP(E43,sheet1!$B$2:$C$3209,2,FALSE) -> 得意先マスター照会 | AF43: 13.得意先マスタ照会 | AG43: PD2220 | AH43: =MID(AF43,4,100) -> 得意先マスタ照会 | AL43: =TRIM(AN43) -> 得意先マスタ照会 | AM43: 〇 | AN43: 得意先マスタ照会 | AO43: =TRIM(MIDB(AQ43,4,99)) -> 得意先マスタ照会 | AP43: =TRIM(AR43) -> PD2220 | AQ43: 13.得意先マスタ照会 | AR43: PD2220 | AS43: =TRIM(MID(AU43,4,99)) -> 得意先マスタ照会 | AT43: =TRIM(AV43) -> PD2220 | AU43: 13.得意先マスタ照会 | AV43: PD2220
A44: 42 | B44: 販売システム | C44: マスター照会 | D44: ー | E44: PD2170 | F44: 取引先マスタ照会 | J44: 〇 | Q44: =VLOOKUP(E44,sheet1!$B$2:$D$3209,3,FALSE) -> 895 | R44: 〇 | S44: 〇 | T44: 〇 | U44: 〇 | V44: 〇 | Z44: 〇 | AB44: 〇 | AC44: 〇 | AD44: =VLOOKUP(E44,sheet1!$B$2:$C$3209,2,FALSE) -> 取引先マスター照会 | AF44: 14.取引先マスタ照会 | AG44: PD2170 | AH44: =MID(AF44,4,100) -> 取引先マスタ照会 | AL44: =TRIM(AN44) -> 取引先マスタ照会 | AM44: 〇 | AN44: 取引先マスタ照会 | AO44: =TRIM(MIDB(AQ44,4,99)) -> 取引先マスタ照会 | AP44: =TRIM(AR44) -> PD2170 | AQ44: 14.取引先マスタ照会 | AR44: PD2170 | AS44: =TRIM(MID(AU44,4,99)) -> 取引先マスタ照会 | AT44: =TRIM(AV44) -> PD2170 | AU44: 14.取引先マスタ照会 | AV44: PD2170
A45: 43 | B45: 販売システム | C45: マスター照会 | D45: ー | E45: SA1670 | F45: ホールマスタ照会 | J45: 〇 | Q45: =VLOOKUP(E45,sheet1!$B$2:$D$3209,3,FALSE) -> 323 | R45: 〇 | S45: 〇 | T45: 〇 | U45: 〇 | V45: 〇 | AB45: 〇 | AC45: 〇 | AD45: =VLOOKUP(E45,sheet1!$B$2:$C$3209,2,FALSE) -> ホールマスター照会 | AF45: 15.ホールマスタ照会 | AG45: SA1670 | AH45: =MID(AF45,4,100) -> ホールマスタ照会 | AL45: =TRIM(AN45) -> ホールマスタ照会 | AM45: 〇 | AN45: ホールマスタ照会 | AO45: =TRIM(MIDB(AQ45,4,99)) -> ホールマスタ照会 | AP45: =TRIM(AR45) -> SA1670 | AQ45: 15.ホールマスタ照会 | AR45: SA1670 | AS45: =TRIM(MID(AU45,4,99)) -> ホールマスタ照会 | AT45: =TRIM(AV45) -> SA1670 | AU45: 15.ホールマスタ照会 | AV45: SA1670
A46: 44 | B46: 販売システム | C46: マスター照会 | D46: ー | E46: SA0221 | F46: 銀行振込口座照会 | J46: 〇 | Q46: =VLOOKUP(E46,sheet1!$B$2:$D$3209,3,FALSE) -> 230 | R46: 〇 | S46: 〇 | T46: 〇 | U46: 〇 | V46: 〇 | Z46: 〇 | AB46: 〇 | AC46: 〇 | AD46: =VLOOKUP(E46,sheet1!$B$2:$C$3209,2,FALSE) -> 銀行振込口座マスター照会 | AF46: 16.銀行振込口座照会 | AG46: SA0221 | AH46: =MID(AF46,4,100) -> 銀行振込口座照会 | AL46: =TRIM(AN46) -> 銀行振込口座照会 | AM46: 〇 | AN46: 銀行振込口座照会 | AO46: =TRIM(MIDB(AQ46,4,99)) -> 銀行振込口座照会 | AP46: =TRIM(AR46) -> SA0221 | AQ46: 16.銀行振込口座照会 | AR46: SA0221 | AS46: =TRIM(MID(AU46,4,99)) -> 銀行振込口座照会 | AT46: =TRIM(AV46) -> SA0221 | AU46: 16.銀行振込口座照会 | AV46: SA0221
A47: 45 | B47: 販売システム | C47: マスター照会 | D47: ー | E47: MM2080 | F47: 請求書発送先照会 | J47: 〇 | Q47: =VLOOKUP(E47,sheet1!$B$2:$D$3209,3,FALSE) -> 429 | R47: 〇 | S47: 〇 | T47: 〇 | U47: 〇 | V47: 〇 | Z47: 〇 | AB47: 〇 | AC47: 〇 | AD47: =VLOOKUP(E47,sheet1!$B$2:$C$3209,2,FALSE) -> 請求書発送先照会 | AF47: 17.請求書発送先照会 | AG47: MM2080 | AH47: =MID(AF47,4,100) -> 請求書発送先照会 | AL47: =TRIM(AN47) -> 請求書発送先照会 | AM47: 〇 | AN47: 請求書発送先照会 | AO47: =TRIM(MIDB(AQ47,4,99)) -> 請求書発送先照会 | AP47: =TRIM(AR47) -> MM2080 | AQ47: 17.請求書発送先照会 | AR47: MM2080 | AS47: =TRIM(MID(AU47,4,99)) -> 請求書発送先照会 | AT47: =TRIM(AV47) -> MM2080 | AU47: 17.請求書発送先照会 | AV47: MM2080
A48: 46 | B48: 販売システム | C48: マスター照会 | D48: ー | E48: SA1610 | F48: 保守契約マスター | J48: 〇 | Q48: =VLOOKUP(E48,sheet1!$B$2:$D$3209,3,FALSE) -> 484 | R48: 〇 | S48: 〇 | T48: 〇 | U48: 〇 | V48: 〇 | Z48: 〇 | AB48: 〇 | AC48: 〇 | AD48: =VLOOKUP(E48,sheet1!$B$2:$C$3209,2,FALSE) -> 保守契約マスター照会 | AF48: 54.保守契約マスター | AG48: SA1610 | AH48: =MID(AF48,4,100) -> 保守契約マスター | AL48: =TRIM(AN48) -> 保守契約マスター | AM48: 〇 | AN48: 保守契約マスター | AO48: =TRIM(MIDB(AQ48,4,99)) -> 保守契約マスター | AP48: =TRIM(AR48) -> SA1610 | AQ48: 54.保守契約マスター | AR48: SA1610 | AS48: =TRIM(MID(AU48,4,99)) -> 保守契約マスター | AT48: =TRIM(AV48) -> SA1610 | AU48: 54.保守契約マスター | AV48: SA1610
A49: 47 | B49: 販売システム | C49: マスター照会 | D49: ー | E49: SA5180 | F49: 与信申請書データ照会 | J49: 〇 | Q49: =VLOOKUP(E49,sheet1!$B$2:$D$3209,3,FALSE) -> 576 | R49: 〇 | S49: 〇 | T49: 〇 | U49: 〇 | V49: 〇 | Z49: 〇 | AB49: 〇 | AC49: 〇 | AD49: =VLOOKUP(E49,sheet1!$B$2:$C$3209,2,FALSE) -> 与信決裁内容照会 | AF49: 55.与信申請書データ照会 | AG49: SA5180 | AH49: =MID(AF49,4,100) -> 与信申請書データ照会 | AL49: =TRIM(AN49) -> 与信申請書データ照会 | AM49: 〇 | AN49: 与信申請書データ照会 | AO49: =TRIM(MIDB(AQ49,4,99)) -> 与信申請書データ照会 | AP49: =TRIM(AR49) -> SA5180 | AQ49: 55.与信申請書データ照会 | AR49: SA5180 | AS49: =TRIM(MID(AU49,4,99)) -> 与信申請書データ照会 | AT49: =TRIM(AV49) -> SA5180 | AU49: 55.与信申請書データ照会 | AV49: SA5180
A50: 48 | B50: 販売システム | C50: マスター一覧表 | D50: ー | E50: SA2040 | F50: 与信マスタ一覧表 | J50: 〇 | Q50: =VLOOKUP(E50,sheet1!$B$2:$D$3209,3,FALSE) -> 1064 | R50: 〇 | S50: 〇 | T50: 〇 | U50: 〇 | V50: 〇 | Z50: 〇 | AB50: 〇 | AC50: 〇 | AD50: =VLOOKUP(E50,sheet1!$B$2:$C$3209,2,FALSE) -> 与信マスター一覧表 | AF50: 01.与信マスタ一覧表 | AG50: SA2040 | AH50: =MID(AF50,4,100) -> 与信マスタ一覧表 | AL50: =TRIM(AN50) -> 与信マスタ一覧表 | AM50: 〇 | AN50: 与信マスタ一覧表 | AO50: =TRIM(MIDB(AQ50,4,99)) -> 与信マスタ一覧表 | AP50: =TRIM(AR50) -> SA2040 | AQ50: 01.与信マスタ一覧表 | AR50: SA2040 | AS50: =TRIM(MID(AU50,4,99)) -> 与信マスタ一覧表 | AT50: =TRIM(AV50) -> SA2040 | AU50: 01.与信マスタ一覧表 | AV50: SA2040
A51: 49 | B51: 販売システム | C51: マスター一覧表 | D51: ー | E51: SA2042 | F51: 与信マスタ一覧＜限度額指定＞ | J51: 〇 | Q51: =VLOOKUP(E51,sheet1!$B$2:$D$3209,3,FALSE) -> 401 | R51: 〇 | S51: 〇 | T51: 〇 | U51: 〇 | V51: 〇 | Z51: 〇 | AB51: 〇 | AC51: 〇 | AD51: =VLOOKUP(E51,sheet1!$B$2:$C$3209,2,FALSE) -> 与信債権対比表＜全件出力＞ | AF51: 02.与信マスタ一覧＜限度額指定＞ | AG51: SA2042 | AH51: =MID(AF51,4,100) -> 与信マスタ一覧＜限度額指定＞ | AL51: =TRIM(AN51) -> 与信マスタ一覧＜限度額指定＞ | AM51: 〇 | AN51: 与信マスタ一覧＜限度額指定＞ | AO51: =TRIM(MIDB(AQ51,4,99)) -> 与信マスタ一覧＜限度額指定＞ | AP51: =TRIM(AR51) -> SA2042 | AQ51: 02.与信マスタ一覧＜限度額指定＞ | AR51: SA2042 | AS51: =TRIM(MID(AU51,4,99)) -> 与信マスタ一覧＜限度額指定＞ | AT51: =TRIM(AV51) -> SA2042 | AU51: 02.与信マスタ一覧＜限度額指定＞ | AV51: SA2042
A52: 50 | B52: 販売システム | C52: マスター一覧表 | D52: ー | E52: SA2050 | F52: 販売価格マスター一覧表 | J52: 〇 | Q52: =VLOOKUP(E52,sheet1!$B$2:$D$3209,3,FALSE) -> 571 | R52: 〇 | S52: 〇 | T52: 〇 | U52: 〇 | V52: 〇 | Z52: 〇 | AB52: 〇 | AC52: 〇 | AD52: =VLOOKUP(E52,sheet1!$B$2:$C$3209,2,FALSE) -> 販売価格マスター一覧表 | AF52: 03.販売価格マスター一覧表 | AG52: SA2050 | AH52: =MID(AF52,4,100) -> 販売価格マスター一覧表 | AL52: =TRIM(AN52) -> 販売価格マスター一覧表 | AM52: 〇 | AN52: 販売価格マスター一覧表 | AO52: =TRIM(MIDB(AQ52,4,99)) -> 販売価格マスター一覧表 | AP52: =TRIM(AR52) -> SA2050 | AQ52: 03.販売価格マスター一覧表 | AR52: SA2050 | AS52: =TRIM(MID(AU52,4,99)) -> 販売価格マスター一覧表 | AT52: =TRIM(AV52) -> SA2050 | AU52: 03.販売価格マスター一覧表 | AV52: SA2050
A53: 51 | B53: 販売システム | C53: マスター一覧表 | D53: ー | E53: ー | F53: 与信限度・債権超過／簡易 | J53: 〇 | Q53: =VLOOKUP(E53,sheet1!$B$2:$D$3209,3,FALSE) -> #N/A | R53: 〇 | S53: 〇 | T53: 〇 | U53: 〇 | V53: 〇 | Z53: 〇 | AB53: 〇 | AC53: 〇 | AD53: =VLOOKUP(E53,sheet1!$B$2:$C$3209,2,FALSE) -> #N/A | AF53: 04.与信限度・債権超過／簡易 | AG53: ー | AH53: =MID(AF53,4,100) -> 与信限度・債権超過／簡易 | AL53: =TRIM(AN53) -> 与信限度・債権超過／簡易 | AM53: 〇 | AN53: 与信限度・債権超過／簡易 | AO53: =TRIM(MIDB(AQ53,4,99)) -> 与信限度・債権超過／簡易 | AP53: =TRIM(AR53) | AQ53: 04.与信限度・債権超過／簡易 | AS53: =TRIM(MID(AU53,4,99)) -> 与信限度・債権超過／簡易 | AT53: =TRIM(AV53) | AU53: 04.与信限度・債権超過／簡易
A54: 52 | B54: 販売システム | C54: マスター一覧表 | D54: ー | E54: MS2710 | F54: 摘要／科目・摘要ﾏｽﾀｰﾘｽﾄ | J54: 〇 | Q54: =VLOOKUP(E54,sheet1!$B$2:$D$3209,3,FALSE) -> 427 | R54: 〇 | S54: 〇 | T54: 〇 | U54: 〇 | V54: 〇 | Z54: 〇 | AB54: 〇 | AC54: 〇 | AD54: =VLOOKUP(E54,sheet1!$B$2:$C$3209,2,FALSE) -> 勘定科目・摘要コード関連データリスト | AF54: 06.摘要／科目・摘要ﾏｽﾀｰﾘｽﾄ | AG54: MS2710 | AH54: =MID(AF54,4,100) -> 摘要／科目・摘要ﾏｽﾀｰﾘｽﾄ | AL54: =TRIM(AN54) -> 摘要／科目・摘要ﾏｽﾀｰﾘｽﾄ | AM54: 〇 | AN54: 摘要／科目・摘要ﾏｽﾀｰﾘｽﾄ | AO54: =TRIM(MIDB(AQ54,4,99)) -> 摘要／科目・摘要ﾏｽﾀｰﾘｽﾄ | AP54: =TRIM(AR54) -> MS2710 | AQ54: 06.摘要／科目・摘要ﾏｽﾀｰﾘｽﾄ | AR54: MS2710 | AS54: =TRIM(MID(AU54,4,99)) -> 摘要／科目・摘要ﾏｽﾀｰﾘｽﾄ | AT54: =TRIM(AV54) -> MS2710 | AU54: 06.摘要／科目・摘要ﾏｽﾀｰﾘｽﾄ | AV54: MS2710
A55: 53 | B55: 販売システム | C55: マスター一覧表 | D55: ー | E55: SA2480 | F55: 修理内容各種マスタ一覧 | J55: 〇 | Q55: =VLOOKUP(E55,sheet1!$B$2:$D$3209,3,FALSE) -> 197 | R55: 〇 | S55: 〇 | T55: 〇 | U55: 〇 | V55: 〇 | Z55: 〇 | AB55: 〇 | AC55: 〇 | AD55: =VLOOKUP(E55,sheet1!$B$2:$C$3209,2,FALSE) -> 修理内容マスタ一覧表 | AF55: 07.修理内容各種マスタ一覧 | AG55: SA2480 | AH55: =MID(AF55,4,100) -> 修理内容各種マスタ一覧 | AL55: =TRIM(AN55) -> 修理内容各種マスタ一覧 | AM55: 〇 | AN55: 修理内容各種マスタ一覧 | AO55: =TRIM(MIDB(AQ55,4,99)) -> 修理内容各種マスタ一覧 | AP55: =TRIM(AR55) -> SA2480 | AQ55: 07.修理内容各種マスタ一覧 | AR55: SA2480 | AS55: =TRIM(MID(AU55,4,99)) -> 修理内容各種マスタ一覧 | AT55: =TRIM(AV55) -> SA2480 | AU55: 07.修理内容各種マスタ一覧 | AV55: SA2480
A56: 54 | B56: 販売システム | C56: マスター一覧表 | D56: ー | E56: ー | F56: 保守契約マスターリスト | J56: 〇 | Q56: =VLOOKUP(E56,sheet1!$B$2:$D$3209,3,FALSE) -> #N/A | R56: 〇 | S56: 〇 | T56: 〇 | U56: 〇 | V56: 〇 | Z56: 〇 | AB56: 〇 | AC56: 〇 | AD56: =VLOOKUP(E56,sheet1!$B$2:$C$3209,2,FALSE) -> #N/A | AF56: 08.保守契約マスターリスト | AG56: ー | AH56: =MID(AF56,4,100) -> 保守契約マスターリスト | AL56: =TRIM(AN56) -> 保守契約マスターリスト | AM56: 〇 | AN56: 保守契約マスターリスト | AO56: =TRIM(MIDB(AQ56,4,99)) -> 保守契約マスターリスト | AP56: =TRIM(AR56) | AQ56: 08.保守契約マスターリスト | AS56: =TRIM(MID(AU56,4,99)) -> 保守契約マスターリスト | AT56: =TRIM(AV56) | AU56: 08.保守契約マスターリスト
A57: 55 | B57: 販売システム | C57: マスター一覧表 | D57: ー | E57: ー | F57: 未保守契約一覧リスト | J57: 〇 | Q57: =VLOOKUP(E57,sheet1!$B$2:$D$3209,3,FALSE) -> #N/A | R57: 〇 | S57: 〇 | T57: 〇 | U57: 〇 | V57: 〇 | Z57: 〇 | AB57: 〇 | AC57: 〇 | AD57: =VLOOKUP(E57,sheet1!$B$2:$C$3209,2,FALSE) -> #N/A | AF57: 09.未保守契約一覧リスト | AG57: ー | AH57: =MID(AF57,4,100) -> 未保守契約一覧リスト | AL57: =TRIM(AN57) -> 未保守契約一覧リスト | AM57: 〇 | AN57: 未保守契約一覧リスト | AO57: =TRIM(MIDB(AQ57,4,99)) -> 未保守契約一覧リスト | AP57: =TRIM(AR57) | AQ57: 09.未保守契約一覧リスト | AS57: =TRIM(MID(AU57,4,99)) -> 未保守契約一覧リスト | AT57: =TRIM(AV57) | AU57: 09.未保守契約一覧リスト
A58: 56 | B58: 販売システム | C58: マスター一覧表 | D58: ー | E58: SA2043 | F58: 与信マスタ一覧表（担当者別） | J58: 〇 | Q58: =VLOOKUP(E58,sheet1!$B$2:$D$3209,3,FALSE) -> 521 | R58: 〇 | S58: 〇 | T58: 〇 | U58: 〇 | V58: 〇 | Z58: 〇 | AB58: 〇 | AC58: 〇 | AD58: =VLOOKUP(E58,sheet1!$B$2:$C$3209,2,FALSE) -> 与信債権対比表＜担当者別＞ | AF58: 10.与信マスタ一覧表（担当者別） | AG58: SA2043 | AH58: =MID(AF58,4,100) -> 与信マスタ一覧表（担当者別） | AL58: =TRIM(AN58) -> 与信マスタ一覧表（担当者別） | AM58: 〇 | AN58: 与信マスタ一覧表（担当者別） | AO58: =TRIM(MIDB(AQ58,4,99)) -> 与信マスタ一覧表（担当者別） | AP58: =TRIM(AR58) -> SA2043 | AQ58: 10.与信マスタ一覧表（担当者別） | AR58: SA2043 | AS58: =TRIM(MID(AU58,4,99)) -> 与信マスタ一覧表（担当者別） | AT58: =TRIM(AV58) -> SA2043 | AU58: 10.与信マスタ一覧表（担当者別） | AV58: SA2043
A59: 57 | B59: 販売システム | C59: 受注・出荷指示メニュー | D59: ー | E59: SA3010 | F59: 受注入力（通常) | J59: 〇 | Q59: =VLOOKUP(E59,sheet1!$B$2:$D$3209,3,FALSE) -> 15697 | R59: 〇 | S59: 〇 | T59: 〇 | U59: 〇 | V59: 〇 | Z59: 〇 | AB59: 〇 | AC59: 〇 | AD59: =VLOOKUP(E59,sheet1!$B$2:$C$3209,2,FALSE) -> 受注入力 ＪＳ与信改善対応 | AF59: 01.受注入力（通常) | AG59: SA3010 | AH59: =MID(AF59,4,100) -> 受注入力（通常) | AL59: =TRIM(AN59) -> 受注入力（通常) | AM59: 〇 | AN59: 受注入力（通常) | AO59: =TRIM(MIDB(AQ59,4,99)) -> 受注入力（通常) | AP59: =TRIM(AR59) -> SA3010 | AQ59: 01.受注入力（通常) | AR59: SA3010 | AS59: =TRIM(MID(AU59,4,99)) -> 受注入力（通常) | AT59: =TRIM(AV59) -> SA3010 | AU59: 01.受注入力（通常) | AV59: SA3010
A60: 58 | B60: 販売システム | C60: 受注・出荷指示メニュー | D60: ー | E60: SA3010 | F60: 受注入力（返品） | J60: 〇 | Q60: =VLOOKUP(E60,sheet1!$B$2:$D$3209,3,FALSE) -> 15697 | R60: 〇 | S60: 〇 | T60: 〇 | U60: 〇 | V60: 〇 | Z60: 〇 | AB60: 〇 | AC60: 〇 | AD60: =VLOOKUP(E60,sheet1!$B$2:$C$3209,2,FALSE) -> 受注入力 ＪＳ与信改善対応 | AF60: 02.受注入力（返品） | AG60: SA3010 | AH60: =MID(AF60,4,100) -> 受注入力（返品） | AL60: =TRIM(AN60) -> 受注入力（返品） | AM60: 〇 | AN60: 受注入力（返品） | AO60: =TRIM(MIDB(AQ60,4,99)) -> 受注入力（返品） | AP60: =TRIM(AR60) -> SA3010 | AQ60: 02.受注入力（返品） | AR60: SA3010 | AS60: =TRIM(MID(AU60,4,99)) -> 受注入力（返品） | AT60: =TRIM(AV60) -> SA3010 | AU60: 02.受注入力（返品） | AV60: SA3010
A61: 59 | B61: 販売システム | C61: 受注・出荷指示メニュー | D61: ー | E61: SA301X | F61: 受注入力（元受注No.検索） | J61: 〇 | Q61: =VLOOKUP(E61,sheet1!$B$2:$D$3209,3,FALSE) -> 15746 | R61: 〇 | S61: 〇 | T61: 〇 | U61: 〇 | V61: 〇 | Z61: 〇 | AB61: 〇 | AC61: 〇 | AD61: =VLOOKUP(E61,sheet1!$B$2:$C$3209,2,FALSE) -> 受注入力ＪＳ与信改善対応・受注検索 | AF61: 03.受注入力（元受注No.検索） | AG61: SA301X | AH61: =MID(AF61,4,100) -> 受注入力（元受注No.検索） | AL61: =TRIM(AN61) -> 受注入力（元受注No.検索） | AM61: 〇 | AN61: 受注入力（元受注No.検索） | AO61: =TRIM(MIDB(AQ61,4,99)) -> 受注入力（元受注No.検索） | AP61: =TRIM(AR61) -> SA301X | AQ61: 03.受注入力（元受注No.検索） | AR61: SA301X | AS61: =TRIM(MID(AU61,4,99)) -> 受注入力（元受注No.検索） | AT61: =TRIM(AV61) -> SA301X | AU61: 03.受注入力（元受注No.検索） | AV61: SA301X
A62: 60 | B62: 販売システム | C62: 受注・出荷指示メニュー | D62: ー | E62: SA3020 | F62: 値引承認入力（通常） | J62: 〇 | Q62: =VLOOKUP(E62,sheet1!$B$2:$D$3209,3,FALSE) -> 750 | R62: 〇 | S62: 〇 | T62: 〇 | U62: 〇 | V62: 〇 | Z62: 〇 | AB62: 〇 | AC62: 〇 | AD62: =VLOOKUP(E62,sheet1!$B$2:$C$3209,2,FALSE) -> 値引承認入力 | AF62: 11.値引承認入力（通常） | AG62: SA3020 | AH62: =MID(AF62,4,100) -> 値引承認入力（通常） | AL62: =TRIM(AN62) -> 値引承認入力（通常） | AM62: 〇 | AN62: 値引承認入力（通常） | AO62: =TRIM(MIDB(AQ62,4,99)) -> 値引承認入力（通常） | AP62: =TRIM(AR62) -> SA3020 | AQ62: 11.値引承認入力（通常） | AR62: SA3020 | AS62: =TRIM(MID(AU62,4,99)) -> 値引承認入力（通常） | AT62: =TRIM(AV62) -> SA3020 | AU62: 11.値引承認入力（通常） | AV62: SA3020
A63: 61 | B63: 販売システム | C63: 受注・出荷指示メニュー | D63: ー | E63: SA3020 | F63: 値引承認入力（返品） | J63: 〇 | Q63: =VLOOKUP(E63,sheet1!$B$2:$D$3209,3,FALSE) -> 750 | R63: 〇 | S63: 〇 | T63: 〇 | U63: 〇 | V63: 〇 | Z63: 〇 | AB63: 〇 | AC63: 〇 | AD63: =VLOOKUP(E63,sheet1!$B$2:$C$3209,2,FALSE) -> 値引承認入力 | AF63: 12.値引承認入力（返品） | AG63: SA3020 | AH63: =MID(AF63,4,100) -> 値引承認入力（返品） | AL63: =TRIM(AN63) -> 値引承認入力（返品） | AM63: 〇 | AN63: 値引承認入力（返品） | AO63: =TRIM(MIDB(AQ63,4,99)) -> 値引承認入力（返品） | AP63: =TRIM(AR63) -> SA3020 | AQ63: 12.値引承認入力（返品） | AR63: SA3020 | AS63: =TRIM(MID(AU63,4,99)) -> 値引承認入力（返品） | AT63: =TRIM(AV63) -> SA3020 | AU63: 12.値引承認入力（返品） | AV63: SA3020
A64: 62 | B64: 販売システム | C64: 受注・出荷指示メニュー | D64: ー | E64: SA3030 | F64: 受注承認入力（通常） | J64: 〇 | Q64: =VLOOKUP(E64,sheet1!$B$2:$D$3209,3,FALSE) -> 4639 | R64: 〇 | S64: 〇 | T64: 〇 | U64: 〇 | V64: 〇 | Z64: 〇 | AB64: 〇 | AC64: 〇 | AD64: =VLOOKUP(E64,sheet1!$B$2:$C$3209,2,FALSE) -> 受注承認入力 ＪＳ与信改善 | AF64: 21.受注承認入力（通常） | AG64: SA3030 | AH64: =MID(AF64,4,100) -> 受注承認入力（通常） | AL64: =TRIM(AN64) -> 受注承認入力（通常） | AM64: 〇 | AN64: 受注承認入力（通常） | AO64: =TRIM(MIDB(AQ64,4,99)) -> 受注承認入力（通常） | AP64: =TRIM(AR64) -> SA3030 | AQ64: 21.受注承認入力（通常） | AR64: SA3030 | AS64: =TRIM(MID(AU64,4,99)) -> 受注承認入力（通常） | AT64: =TRIM(AV64) -> SA3030 | AU64: 21.受注承認入力（通常） | AV64: SA3030
A65: 63 | B65: 販売システム | C65: 受注・出荷指示メニュー | D65: ー | E65: SA3030 | F65: 受注承認入力（返品） | J65: 〇 | Q65: =VLOOKUP(E65,sheet1!$B$2:$D$3209,3,FALSE) -> 4639 | R65: 〇 | S65: 〇 | T65: 〇 | U65: 〇 | V65: 〇 | Z65: 〇 | AB65: 〇 | AC65: 〇 | AD65: =VLOOKUP(E65,sheet1!$B$2:$C$3209,2,FALSE) -> 受注承認入力 ＪＳ与信改善 | AF65: 22.受注承認入力（返品） | AG65: SA3030 | AH65: =MID(AF65,4,100) -> 受注承認入力（返品） | AL65: =TRIM(AN65) -> 受注承認入力（返品） | AM65: 〇 | AN65: 受注承認入力（返品） | AO65: =TRIM(MIDB(AQ65,4,99)) -> 受注承認入力（返品） | AP65: =TRIM(AR65) -> SA3030 | AQ65: 22.受注承認入力（返品） | AR65: SA3030 | AS65: =TRIM(MID(AU65,4,99)) -> 受注承認入力（返品） | AT65: =TRIM(AV65) -> SA3030 | AU65: 22.受注承認入力（返品） | AV65: SA3030
A66: 64 | B66: 販売システム | C66: 受注・出荷指示メニュー | D66: ー | E66: ー | F66: 修理作業依頼書作成 | J66: 〇 | V66: 〇 | Z66: 〇 | AB66: 〇 | AC66: 〇 | AF66: 25.修理作業依頼書作成 | AG66: ー | AH66: =MID(AF66,4,100) -> 修理作業依頼書作成 | AL66: =TRIM(AN66) -> 修理作業依頼書作成 | AM66: 〇 | AN66: 修理作業依頼書作成 | AO66: =TRIM(MIDB(AQ66,4,99)) | AP66: =TRIM(AR66) | AS66: =TRIM(MID(AU66,4,99)) | AT66: =TRIM(AV66)
A67: 65 | B67: 販売システム | C67: 受注・出荷指示メニュー | D67: ー | E67: SA3040 | F67: 出荷指示荷姿入力（製品） | J67: 〇 | Q67: =VLOOKUP(E67,sheet1!$B$2:$D$3209,3,FALSE) -> 2522 | R67: 〇 | S67: 〇 | T67: 〇 | U67: 〇 | V67: 〇 | Z67: 〇 | AB67: 〇 | AC67: 〇 | AD67: =VLOOKUP(E67,sheet1!$B$2:$C$3209,2,FALSE) -> 出荷指示荷姿入力（製品・商品) | AF67: 31.出荷指示荷姿入力（製品） | AG67: SA3040 | AH67: =MID(AF67,4,100) -> 出荷指示荷姿入力（製品） | AL67: =TRIM(AN67) -> 出荷指示荷姿入力（製品） | AM67: 〇 | AN67: 出荷指示荷姿入力（製品） | AO67: =TRIM(MIDB(AQ67,4,99)) -> 出荷指示荷姿入力（製品） | AP67: =TRIM(AR67) -> SA3040 | AQ67: 31.出荷指示荷姿入力（製品） | AR67: SA3040 | AS67: =TRIM(MID(AU67,4,99)) -> 出荷指示荷姿入力（製品） | AT67: =TRIM(AV67) -> SA3040 | AU67: 31.出荷指示荷姿入力（製品） | AV67: SA3040
A68: 66 | B68: 販売システム | C68: 受注・出荷指示メニュー | D68: ー | E68: SA3050 | F68: 出荷指示荷姿入力(ｻｰﾋﾞｽ) | J68: 〇 | Q68: =VLOOKUP(E68,sheet1!$B$2:$D$3209,3,FALSE) -> 1969 | R68: 〇 | S68: 〇 | T68: 〇 | U68: 〇 | V68: 〇 | Z68: 〇 | AB68: 〇 | AC68: 〇 | AD68: =VLOOKUP(E68,sheet1!$B$2:$C$3209,2,FALSE) -> 出荷指示荷姿入力（ｻｰﾋﾞｽﾊﾟｰﾂ ) | AF68: 32.出荷指示荷姿入力(ｻｰﾋﾞｽ) | AG68: SA3050 | AH68: =MID(AF68,4,100) -> 出荷指示荷姿入力(ｻｰﾋﾞｽ) | AL68: =TRIM(AN68) -> 出荷指示荷姿入力(ｻｰﾋﾞｽ) | AM68: 〇 | AN68: 出荷指示荷姿入力(ｻｰﾋﾞｽ) | AO68: =TRIM(MIDB(AQ68,4,99)) -> 出荷指示荷姿入力(ｻｰﾋﾞｽ) | AP68: =TRIM(AR68) -> SA3050 | AQ68: 32.出荷指示荷姿入力(ｻｰﾋﾞｽ) | AR68: SA3050 | AS68: =TRIM(MID(AU68,4,99)) -> 出荷指示荷姿入力(ｻｰﾋﾞｽ) | AT68: =TRIM(AV68) -> SA3050 | AU68: 32.出荷指示荷姿入力(ｻｰﾋﾞｽ) | AV68: SA3050
A69: 67 | B69: 販売システム | C69: 受注・出荷指示メニュー | D69: ー | E69: SA3060 | F69: 出荷指示荷姿最終確認入力 | J69: 〇 | Q69: =VLOOKUP(E69,sheet1!$B$2:$D$3209,3,FALSE) -> 512 | R69: 〇 | S69: 〇 | T69: 〇 | U69: 〇 | V69: 〇 | Z69: 〇 | AB69: 〇 | AC69: 〇 | AD69: =VLOOKUP(E69,sheet1!$B$2:$C$3209,2,FALSE) -> 出荷指示荷姿最終確認入力 | AF69: 33.出荷指示荷姿最終確認入力 | AG69: SA3060 | AH69: =MID(AF69,4,100) -> 出荷指示荷姿最終確認入力 | AL69: =TRIM(AN69) -> 出荷指示荷姿最終確認入力 | AM69: 〇 | AN69: 出荷指示荷姿最終確認入力 | AO69: =TRIM(MIDB(AQ69,4,99)) -> 出荷指示荷姿最終確認入力 | AP69: =TRIM(AR69) -> SA3060 | AQ69: 33.出荷指示荷姿最終確認入力 | AR69: SA3060 | AS69: =TRIM(MID(AU69,4,99)) -> 出荷指示荷姿最終確認入力 | AT69: =TRIM(AV69) -> SA3060 | AU69: 33.出荷指示荷姿最終確認入力 | AV69: SA3060
A70: 68 | B70: 販売システム | C70: 受注・出荷指示メニュー | D70: ー | E70: SA3160 | F70: 請求方法入力 | J70: 〇 | Q70: =VLOOKUP(E70,sheet1!$B$2:$D$3209,3,FALSE) -> 2213 | R70: 〇 | S70: 〇 | T70: 〇 | U70: 〇 | V70: 〇 | Z70: 〇 | AB70: 〇 | AC70: 〇 | AD70: =VLOOKUP(E70,sheet1!$B$2:$C$3209,2,FALSE) -> 請求方法入力 | AF70: 41.請求方法入力 | AG70: SA3160 | AH70: =MID(AF70,4,100) -> 請求方法入力 | AL70: =TRIM(AN70) -> 請求方法入力 | AM70: 〇 | AN70: 請求方法入力 | AO70: =TRIM(MIDB(AQ70,4,99)) -> 請求方法入力 | AP70: =TRIM(AR70) -> SA3160 | AQ70: 41.請求方法入力 | AR70: SA3160 | AS70: =TRIM(MID(AU70,4,99)) -> 請求方法入力 | AT70: =TRIM(AV70) -> SA3160 | AU70: 41.請求方法入力 | AV70: SA3160
A71: 69 | B71: 販売システム | C71: 受注・出荷指示メニュー | D71: ー | E71: SA3151 | F71: 引当振替入力(ｼﾘｱﾙ品目) | J71: 〇 | Q71: =VLOOKUP(E71,sheet1!$B$2:$D$3209,3,FALSE) -> 1355 | R71: 〇 | S71: 〇 | T71: 〇 | U71: 〇 | V71: 〇 | Z71: 〇 | AB71: 〇 | AC71: 〇 | AD71: =VLOOKUP(E71,sheet1!$B$2:$C$3209,2,FALSE) -> 引当振替入力(ｼﾘｱﾙのみ) | AF71: 42.引当振替入力(ｼﾘｱﾙ品目) | AG71: SA3151 | AH71: =MID(AF71,4,100) -> 引当振替入力(ｼﾘｱﾙ品目) | AL71: =TRIM(AN71) -> 引当振替入力(ｼﾘｱﾙ品目) | AM71: 〇 | AN71: 引当振替入力(ｼﾘｱﾙ品目) | AO71: =TRIM(MIDB(AQ71,4,99)) -> 引当振替入力(ｼﾘｱﾙ品目) | AP71: =TRIM(AR71) -> SA3151 | AQ71: 42.引当振替入力(ｼﾘｱﾙ品目) | AR71: SA3151 | AS71: =TRIM(MID(AU71,4,99)) -> 引当振替入力(ｼﾘｱﾙ品目) | AT71: =TRIM(AV71) -> SA3151 | AU71: 42.引当振替入力(ｼﾘｱﾙ品目) | AV71: SA3151
A72: 70 | B72: 販売システム | C72: 受注・出荷指示メニュー | D72: ー | E72: SA3152 | F72: 引当振替入力(受入ﾛｯﾄ品目) | J72: 〇 | Q72: =VLOOKUP(E72,sheet1!$B$2:$D$3209,3,FALSE) -> 1976 | R72: 〇 | S72: 〇 | T72: 〇 | U72: 〇 | V72: 〇 | Z72: 〇 | AB72: 〇 | AC72: 〇 | AD72: =VLOOKUP(E72,sheet1!$B$2:$C$3209,2,FALSE) -> 引当振替入力(ｼﾘｱﾙ以外) | AF72: 43.引当振替入力(受入ﾛｯﾄ品目) | AG72: SA3152 | AH72: =MID(AF72,4,100) -> 引当振替入力(受入ﾛｯﾄ品目) | AL72: =TRIM(AN72) -> 引当振替入力(受入ﾛｯﾄ品目) | AM72: 〇 | AN72: 引当振替入力(受入ﾛｯﾄ品目) | AO72: =TRIM(MIDB(AQ72,4,99)) -> 引当振替入力(受入ﾛｯﾄ品目) | AP72: =TRIM(AR72) -> SA3152 | AQ72: 43.引当振替入力(受入ﾛｯﾄ品目) | AR72: SA3152 | AS72: =TRIM(MID(AU72,4,99)) -> 引当振替入力(受入ﾛｯﾄ品目) | AT72: =TRIM(AV72) -> SA3152 | AU72: 43.引当振替入力(受入ﾛｯﾄ品目) | AV72: SA3152
A73: 71 | B73: 販売システム | C73: 受注・出荷指示メニュー | D73: ー | E73: SA5010 | F73: 受注進捗状況照会 | J73: 〇 | Q73: =VLOOKUP(E73,sheet1!$B$2:$D$3209,3,FALSE) -> 662 | R73: 〇 | S73: 〇 | T73: 〇 | U73: 〇 | V73: 〇 | Z73: 〇 | AB73: 〇 | AC73: 〇 | AD73: =VLOOKUP(E73,sheet1!$B$2:$C$3209,2,FALSE) -> 受注照会 | AF73: 51.受注進捗状況照会 | AG73: SA5010 | AH73: =MID(AF73,4,100) -> 受注進捗状況照会 | AL73: =TRIM(AN73) -> 受注進捗状況照会 | AM73: 〇 | AN73: 受注進捗状況照会 | AO73: =TRIM(MIDB(AQ73,4,99)) -> 受注進捗状況照会 | AP73: =TRIM(AR73) -> SA5010 | AQ73: 51.受注進捗状況照会 | AR73: SA5010 | AS73: =TRIM(MID(AU73,4,99)) -> 受注進捗状況照会 | AT73: =TRIM(AV73) -> SA5010 | AU73: 51.受注進捗状況照会 | AV73: SA5010
A74: 72 | B74: 販売システム | C74: 受注・出荷指示メニュー | D74: ー | E74: SA5012 | F74: 受注引当状況照会 | J74: 〇 | Q74: =VLOOKUP(E74,sheet1!$B$2:$D$3209,3,FALSE) -> 690 | R74: 〇 | S74: 〇 | T74: 〇 | U74: 〇 | V74: 〇 | Z74: 〇 | AB74: 〇 | AC74: 〇 | AD74: =VLOOKUP(E74,sheet1!$B$2:$C$3209,2,FALSE) -> 受注照会 | AF74: 52.受注引当状況照会 | AG74: SA5012 | AH74: =MID(AF74,4,100) -> 受注引当状況照会 | AL74: =TRIM(AN74) -> 受注引当状況照会 | AM74: 〇 | AN74: 受注引当状況照会 | AO74: =TRIM(MIDB(AQ74,4,99)) -> 受注引当状況照会 | AP74: =TRIM(AR74) -> SA5012 | AQ74: 52.受注引当状況照会 | AR74: SA5012 | AS74: =TRIM(MID(AU74,4,99)) -> 受注引当状況照会 | AT74: =TRIM(AV74) -> SA5012 | AU74: 52.受注引当状況照会 | AV74: SA5012
A75: 73 | B75: 販売システム | C75: 受注・出荷指示メニュー | D75: ー | E75: SA3152 | F75: 在庫引当状況照会 | J75: 〇 | Q75: =VLOOKUP(E75,sheet1!$B$2:$D$3209,3,FALSE) -> 1976 | R75: 〇 | S75: 〇 | T75: 〇 | U75: 〇 | V75: 〇 | Z75: 〇 | AB75: 〇 | AC75: 〇 | AD75: =VLOOKUP(E75,sheet1!$B$2:$C$3209,2,FALSE) -> 引当振替入力(ｼﾘｱﾙ以外) | AF75: 53.在庫引当状況照会 | AG75: SA3152 | AH75: =MID(AF75,4,100) -> 在庫引当状況照会 | AL75: =TRIM(AN75) -> 在庫引当状況照会 | AM75: 〇 | AN75: 在庫引当状況照会 | AO75: =TRIM(MIDB(AQ75,4,99)) -> 在庫引当状況照会 | AP75: =TRIM(AR75) -> SA3152 | AQ75: 53.在庫引当状況照会 | AR75: SA3152 | AS75: =TRIM(MID(AU75,4,99)) -> 在庫引当状況照会 | AT75: =TRIM(AV75) -> SA3152 | AU75: 53.在庫引当状況照会 | AV75: SA3152
A76: 74 | B76: 販売システム | C76: 受注・出荷指示メニュー | D76: ー | E76: SA5020 | F76: 受注照会・受注NO指定 | J76: 〇 | Q76: =VLOOKUP(E76,sheet1!$B$2:$D$3209,3,FALSE) -> 2232 | R76: 〇 | S76: 〇 | T76: 〇 | U76: 〇 | V76: 〇 | Z76: 〇 | AB76: 〇 | AC76: 〇 | AD76: =VLOOKUP(E76,sheet1!$B$2:$C$3209,2,FALSE) -> 受注照会 | AF76: 54.受注照会・受注NO指定 | AG76: SA5020 | AH76: =MID(AF76,4,100) -> 受注照会・受注NO指定 | AL76: =TRIM(AN76) -> 受注照会・受注NO指定 | AM76: 〇 | AN76: 受注照会・受注NO指定 | AO76: =TRIM(MIDB(AQ76,4,99)) -> 受注照会・受注NO指定 | AP76: =TRIM(AR76) -> SA5020 | AQ76: 54.受注照会・受注NO指定 | AR76: SA5020 | AS76: =TRIM(MID(AU76,4,99)) -> 受注照会・受注NO指定 | AT76: =TRIM(AV76) -> SA5020 | AU76: 54.受注照会・受注NO指定 | AV76: SA5020
A77: 75 | B77: 販売システム | C77: 受注・出荷指示メニュー | D77: ー | E77: PD9150 | F77: シリアル詳細情報照会 | J77: 〇 | Q77: =VLOOKUP(E77,sheet1!$B$2:$D$3209,3,FALSE) -> 197 | R77: 〇 | S77: 〇 | T77: 〇 | U77: 〇 | V77: 〇 | Z77: 〇 | AB77: 〇 | AC77: 〇 | AD77: =VLOOKUP(E77,sheet1!$B$2:$C$3209,2,FALSE) -> 参照ﾗｲﾌﾞﾗﾘ指定 | AF77: 55.シリアル詳細情報照会 | AG77: PD9150 | AH77: =MID(AF77,4,100) -> シリアル詳細情報照会 | AL77: =TRIM(AN77) -> シリアル詳細情報照会 | AM77: 〇 | AN77: シリアル詳細情報照会 | AO77: =TRIM(MIDB(AQ77,4,99)) -> シリアル詳細情報照会 | AP77: =TRIM(AR77) -> PD9150 | AQ77: 55.シリアル詳細情報照会 | AR77: PD9150 | AS77: =TRIM(MID(AU77,4,99)) -> シリアル詳細情報照会 | AT77: =TRIM(AV77) -> PD9150 | AU77: 55.シリアル詳細情報照会 | AV77: PD9150
A78: 76 | B78: 販売システム | C78: 受注・出荷指示メニュー | D78: ー | E78: SA5110 | F78: 受注照会・品目ｺｰﾄﾞ指定 | J78: 〇 | Q78: =VLOOKUP(E78,sheet1!$B$2:$D$3209,3,FALSE) -> 418 | R78: 〇 | S78: 〇 | T78: 〇 | U78: 〇 | V78: 〇 | Z78: 〇 | AB78: 〇 | AC78: 〇 | AD78: =VLOOKUP(E78,sheet1!$B$2:$C$3209,2,FALSE) -> 受注照会（品目番号検索） | AF78: 56.受注照会・品目ｺｰﾄﾞ指定 | AG78: SA5110 | AH78: =MID(AF78,4,100) -> 受注照会・品目ｺｰﾄﾞ指定 | AL78: =TRIM(AN78) -> 受注照会・品目ｺｰﾄﾞ指定 | AM78: 〇 | AN78: 受注照会・品目ｺｰﾄﾞ指定 | AO78: =TRIM(MIDB(AQ78,4,99)) -> 受注照会・品目ｺｰﾄﾞ指定 | AP78: =TRIM(AR78) -> SA5110 | AQ78: 56.受注照会・品目ｺｰﾄﾞ指定 | AR78: SA5110 | AS78: =TRIM(MID(AU78,4,99)) -> 受注照会・品目ｺｰﾄﾞ指定 | AT78: =TRIM(AV78) -> SA5110 | AU78: 56.受注照会・品目ｺｰﾄﾞ指定 | AV78: SA5110
... A84: 82 | B84: 販売システム | C84: 受注・出荷指示メニュー | D84: ー | E84: SA2030 | F84: 生産計画依頼リスト | J84: 〇 | Q84: =VLOOKUP(E84,sheet1!$B$2:$D$3209,3,FALSE) -> 563 | R84: 〇 | S84: 〇 | T84: 〇 | U84: 〇 | V84: 〇 | Z84: 〇 | AB84: 〇 | AC84: 〇 | AD84: =VLOOKUP(E84,sheet1!$B$2:$C$3209,2,FALSE) -> 生産計画依頼リスト | AF84: 64.生産計画依頼リスト | AG84: SA2030 | AH84: =MID(AF84,4,100) -> 生産計画依頼リスト | AL84: =TRIM(AN84) -> 生産計画依頼リスト | AM84: 〇 | AN84: 生産計画依頼リスト | AO84: =TRIM(MIDB(AQ84,4,99)) -> 生産計画依頼リスト | AP84: =TRIM(AR84) -> SA2030 | AQ84: 64.生産計画依頼リスト | AR84: SA2030 | AS84: =TRIM(MID(AU84,4,99)) -> 生産計画依頼リスト | AT84: =TRIM(AV84) -> SA2030 | AU84: 64.生産計画依頼リスト | AV84: SA2030
A85: 83 | B85: 販売システム | C85: 受注・出荷指示メニュー | D85: ー | E85: PD0120 | F85: 発送先マスターメンテ | J85: 〇 | Q85: =VLOOKUP(E85,sheet1!$B$2:$D$3209,3,FALSE) -> 1587 | R85: 〇 | S85: 〇 | T85: 〇 | U85: 〇 | V85: 〇 | Z85: 〇 | AA85: 〇 | AB85: 〇 | AC85: 〇 | AD85: =VLOOKUP(E85,sheet1!$B$2:$C$3209,2,FALSE) -> 取引先マスターメンテナンス | AF85: 65.発送先マスターメンテ | AG85: PD0120 | AH85: =MID(AF85,4,100) -> 発送先マスターメンテ | AL85: =TRIM(AN85) -> 発送先マスターメンテ | AM85: 〇 | AN85: 発送先マスターメンテ | AO85: =TRIM(MIDB(AQ85,4,99)) -> 発送先マスターメンテ | AP85: =TRIM(AR85) -> PD0120 | AQ85: 65.発送先マスターメンテ | AR85: PD0120 | AS85: =TRIM(MID(AU85,4,99)) -> 発送先マスターメンテ | AT85: =TRIM(AV85) -> PD0120 | AU85: 65.発送先マスターメンテ | AV85: PD0120
A86: 84 | B86: 販売システム | C86: 受注・出荷指示メニュー | D86: ー | E86: SA2360C | F86: ｻｰﾋﾞｽﾊﾟｰﾂｵｰﾀﾞｰｼｰﾄ | J86: 〇 | Q86: =VLOOKUP(E86,sheet1!$B$2:$D$3209,3,FALSE) -> 13 | R86: 〇 | S86: 〇 | T86: 〇 | U86: 〇 | V86: 〇 | Z86: 〇 | AB86: 〇 | AC86: 〇 | AD86: =VLOOKUP(E86,sheet1!$B$2:$C$3209,2,FALSE) -> サービスパーツオーダーシート | AF86: 66.ｻｰﾋﾞｽﾊﾟｰﾂｵｰﾀﾞｰｼｰﾄ | AG86: SA2360C | AH86: =MID(AF86,4,100) -> ｻｰﾋﾞｽﾊﾟｰﾂｵｰﾀﾞｰｼｰﾄ | AL86: =TRIM(AN86) -> ｻｰﾋﾞｽﾊﾟｰﾂｵｰﾀﾞｰｼｰﾄ | AM86: 〇 | AN86: ｻｰﾋﾞｽﾊﾟｰﾂｵｰﾀﾞｰｼｰﾄ | AO86: =TRIM(MIDB(AQ86,4,99)) -> ｻｰﾋﾞｽﾊﾟｰﾂｵｰﾀﾞｰｼｰﾄ | AP86: =TRIM(AR86) -> SA2360 | AQ86: 66. ｻｰﾋﾞｽﾊﾟｰﾂｵｰﾀﾞｰｼｰﾄ | AR86: SA2360 | AS86: =TRIM(MID(AU86,4,99)) -> ｻｰﾋﾞｽﾊﾟｰﾂｵｰﾀﾞｰｼｰﾄ | AT86: =TRIM(AV86) -> SA2360 | AU86: 66. ｻｰﾋﾞｽﾊﾟｰﾂｵｰﾀﾞｰｼｰﾄ | AV86: SA2360
A87: 85 | B87: 販売システム | C87: 受注・出荷指示メニュー | D87: ー | E87: SA2395C | F87: 受注一覧表ダウンロード | J87: 〇 | Q87: =VLOOKUP(E87,sheet1!$B$2:$D$3209,3,FALSE) -> 54 | R87: 〇 | S87: 〇 | T87: 〇 | U87: 〇 | V87: 〇 | Z87: 〇 | AB87: 〇 | AC87: 〇 | AD87: =VLOOKUP(E87,sheet1!$B$2:$C$3209,2,FALSE) -> 受注一覧表ｴｸｾﾙﾀﾞｳﾝﾛｰﾄﾞ | AF87: 67.受注一覧表ダウンロード | AG87: SA2395C | AH87: =MID(AF87,4,100) -> 受注一覧表ダウンロード | AL87: =TRIM(AN87) -> 受注一覧表ダウンロード | AM87: 〇 | AN87: 受注一覧表ダウンロード | AO87: =TRIM(MIDB(AQ87,4,99)) -> 受注一覧表ダウンロード | AP87: =TRIM(AR87) -> SA2395 | AQ87: 67.受注一覧表ダウンロード | AR87: SA2395 | AS87: =TRIM(MID(AU87,4,99)) -> 受注一覧表ダウンロード | AT87: =TRIM(AV87) -> SA2395 | AU87: 67.受注一覧表ダウンロード | AV87: SA2395
A88: 86 | B88: 販売システム | C88: 受注・出荷指示メニュー | D88: ー | E88: SA2370C | F88: 部課別販売客先別受注残ﾘｽﾄ | J88: 〇 | Q88: =VLOOKUP(E88,sheet1!$B$2:$D$3209,3,FALSE) -> 12 | R88: 〇 | S88: 〇 | T88: 〇 | U88: 〇 | V88: 〇 | Z88: 〇 | AB88: 〇 | AC88: 〇 | AD88: =VLOOKUP(E88,sheet1!$B$2:$C$3209,2,FALSE) -> 部課別販売客先別受注残ﾘｽﾄ | AF88: 71.部課別販売客先別受注残ﾘｽﾄ | AG88: SA2370C | AH88: =MID(AF88,4,100) -> 部課別販売客先別受注残ﾘｽﾄ | AL88: =TRIM(AN88) -> 部課別販売客先別受注残ﾘｽﾄ | AM88: 〇 | AN88: 部課別販売客先別受注残ﾘｽﾄ | AO88: =TRIM(MIDB(AQ88,4,99)) -> 部課別販売客先別受注残ﾘｽﾄ | AP88: =TRIM(AR88) -> SA2370 | AQ88: 71.部課別販売客先別受注残ﾘｽﾄ | AR88: SA2370 | AS88: =TRIM(MID(AU88,4,99)) -> 部課別販売客先別受注残ﾘｽﾄ | AT88: =TRIM(AV88) -> SA2370 | AU88: 71.部課別販売客先別受注残ﾘｽﾄ | AV88: SA2370
A89: 87 | B89: 販売システム | C89: 出荷管理業務 | D89: ー | E89: SA2110 | F89: 出荷指示書作成 | J89: 〇 | Q89: =VLOOKUP(E89,sheet1!$B$2:$D$3209,3,FALSE) -> 2517 | R89: 〇 | S89: 〇 | T89: 〇 | U89: 〇 | V89: 〇 | Z89: 〇 | AB89: 〇 | AC89: 〇 | AD89: =VLOOKUP(E89,sheet1!$B$2:$C$3209,2,FALSE) -> 出荷指示書作成 | AF89: 01.出荷指示書作成 | AG89: SA2110 | AH89: =MID(AF89,4,100) -> 出荷指示書作成 | AL89: =TRIM(AN89) -> 出荷指示書作成 | AM89: 〇 | AN89: 出荷指示書作成 | AO89: =TRIM(MIDB(AQ89,4,99)) -> 出荷指示書作成 | AP89: =TRIM(AR89) -> SA2110 | AQ89: 01.出荷指示書作成 | AR89: SA2110 | AS89: =TRIM(MID(AU89,4,99)) -> 出荷指示書作成 | AT89: =TRIM(AV89) -> SA2110 | AU89: 01.出荷指示書作成 | AV89: SA2110
A90: 88 | B90: 販売システム | C90: 出荷管理業務 | D90: ー | E90: SA2170 | F90: 送り状作成 | J90: 〇 | Q90: =VLOOKUP(E90,sheet1!$B$2:$D$3209,3,FALSE) -> 936 | R90: 〇 | S90: 〇 | T90: 〇 | U90: 〇 | V90: 〇 | Z90: 〇 | AB90: 〇 | AC90: 〇 | AD90: =VLOOKUP(E90,sheet1!$B$2:$C$3209,2,FALSE) -> 送り状作成指示 | AF90: 02.送り状作成 | AG90: SA2170 | AH90: =MID(AF90,4,100) -> 送り状作成 | AL90: =TRIM(AN90) -> 出荷納品書作成 | AM90: 〇 | AN90: 出荷納品書作成 | AO90: =TRIM(MIDB(AQ90,4,99)) -> 送り状作成 | AP90: =TRIM(AR90) -> SA2170 | AQ90: 02.送り状作成 | AR90: SA2170 | AS90: =TRIM(MID(AU90,4,99)) -> 送り状作成 | AT90: =TRIM(AV90) -> SA2170 | AU90: 02.送り状作成 | AV90: SA2170
A91: 89 | B91: 販売システム | C91: 出荷管理業務 | D91: ー | E91: SA2210 | F91: 個口シール作成 | J91: 〇 | Q91: =VLOOKUP(E91,sheet1!$B$2:$D$3209,3,FALSE) -> 606 | R91: 〇 | S91: 〇 | T91: 〇 | U91: 〇 | V91: 〇 | Z91: 〇 | AB91: 〇 | AC91: 〇 | AD91: =VLOOKUP(E91,sheet1!$B$2:$C$3209,2,FALSE) -> 荷造タックシール作成 | AF91: 03.個口シール作成 | AG91: SA2210 | AH91: =MID(AF91,4,100) -> 個口シール作成 | AL91: =TRIM(AN91) -> 送り状作成 | AM91: 〇 | AN91: 送り状作成 | AO91: =TRIM(MIDB(AQ91,4,99)) -> 個口シール作成 | AP91: =TRIM(AR91) -> SA2210 | AQ91: 03.個口シール作成 | AR91: SA2210 | AS91: =TRIM(MID(AU91,4,99)) -> 個口シール作成 | AT91: =TRIM(AV91) -> SA2210 | AU91: 03.個口シール作成 | AV91: SA2210
A92: 90 | B92: 販売システム | C92: 出荷管理業務 | D92: ー | E92: SA2530 | F92: ケースマークシール作成 | J92: 〇 | Q92: =VLOOKUP(E92,sheet1!$B$2:$D$3209,3,FALSE) -> 282 | R92: 〇 | S92: 〇 | T92: 〇 | U92: 〇 | V92: 〇 | Z92: 〇 | AA92: 〇 | AB92: 〇 | AC92: 〇 | AD92: =VLOOKUP(E92,sheet1!$B$2:$C$3209,2,FALSE) -> ｹｰｽﾏｰｸｼｰﾙ発行 | AF92: 04.ケースマークシール作成 | AG92: SA2530 | AH92: =MID(AF92,4,100) -> ケースマークシール作成 | AL92: =TRIM(AN92) -> 個口シール作成 | AM92: 〇 | AN92: 個口シール作成 | AO92: =TRIM(MIDB(AQ92,4,99)) -> ケースマークシール作成 | AP92: =TRIM(AR92) -> SA2530 | AQ92: 04.ケースマークシール作成 | AR92: SA2530 | AS92: =TRIM(MID(AU92,4,99)) -> ケースマークシール作成 | AT92: =TRIM(AV92) -> SA2530 | AU92: 04.ケースマークシール作成 | AV92: SA2530
A93: 91 | B93: 販売システム | C93: 出荷管理業務 | D93: ー | E93: ー | F93: 出荷納品書作成 | J93: 〇 | Q93: =VLOOKUP(E93,sheet1!$B$2:$D$3209,3,FALSE) -> #N/A | R93: 〇 | S93: 〇 | T93: 〇 | U93: 〇 | V93: 〇 | Z93: 〇 | AB93: 〇 | AC93: 〇 | AD93: =VLOOKUP(E93,sheet1!$B$2:$C$3209,2,FALSE) -> #N/A | AF93: 05.出荷納品書作成 | AG93: ー | AH93: =MID(AF93,4,100) -> 出荷納品書作成 | AL93: =TRIM(AN93) -> ケースマークシール作成 | AM93: 〇 | AN93: ケースマークシール作成 | AO93: =TRIM(MIDB(AQ93,4,99)) -> 出荷納品書作成 | AP93: =TRIM(AR93) | AQ93: 05.出荷納品書作成 | AS93: =TRIM(MID(AU93,4,99)) -> 出荷納品書作成 | AT93: =TRIM(AV93) | AU93: 05.出荷納品書作成
A94: 92 | B94: 販売システム | C94: 出荷管理業務 | D94: ー | E94: SA3070 | F94: 出荷実績入力 | J94: 〇 | Q94: =VLOOKUP(E94,sheet1!$B$2:$D$3209,3,FALSE) -> 9567 | R94: 〇 | S94: 〇 | T94: 〇 | U94: 〇 | V94: 〇 | Z94: 〇 | AB94: 〇 | AC94: 〇 | AD94: =VLOOKUP(E94,sheet1!$B$2:$C$3209,2,FALSE) -> 出荷実績入力 | AF94: 11.出荷実績入力 | AG94: SA3070 | AH94: =MID(AF94,4,100) -> 出荷実績入力 | AL94: =TRIM(AN94) -> 出荷実績入力 | AM94: 〇 | AN94: 出荷実績入力 | AO94: =TRIM(MIDB(AQ94,4,99)) -> 出荷実績入力 | AP94: =TRIM(AR94) -> SA3070 | AQ94: 11.出荷実績入力 | AR94: SA3070 | AS94: =TRIM(MID(AU94,4,99)) -> 出荷実績入力 | AT94: =TRIM(AV94) -> SA3070 | AU94: 11.出荷実績入力 | AV94: SA3070
A95: 93 | B95: 販売システム | C95: 出荷管理業務 | D95: ー | E95: SA3180 | F95: 仕様出荷実績入力 | J95: 〇 | Q95: =VLOOKUP(E95,sheet1!$B$2:$D$3209,3,FALSE) -> 2202 | R95: 〇 | S95: 〇 | T95: 〇 | U95: 〇 | V95: 〇 | Z95: 〇 | AB95: 〇 | AC95: 〇 | AD95: =VLOOKUP(E95,sheet1!$B$2:$C$3209,2,FALSE) -> 仕様出荷実績入力 | AF95: 12.仕様出荷実績入力 | AG95: SA3180 | AH95: =MID(AF95,4,100) -> 仕様出荷実績入力 | AL95: =TRIM(AN95) -> 仕様出荷実績入力 | AM95: 〇 | AN95: 仕様出荷実績入力 | AO95: =TRIM(MIDB(AQ95,4,99)) -> 仕様出荷実績入力 | AP95: =TRIM(AR95) -> SA3180 | AQ95: 12.仕様出荷実績入力 | AR95: SA3180 | AS95: =TRIM(MID(AU95,4,99)) -> 仕様出荷実績入力 | AT95: =TRIM(AV95) -> SA3180 | AU95: 12.仕様出荷実績入力 | AV95: SA3180
A96: 94 | B96: 販売システム | C96: 出荷管理業務 | D96: ー | E96: SA3100 | F96: 返品実績入力 | J96: 〇 | Q96: =VLOOKUP(E96,sheet1!$B$2:$D$3209,3,FALSE) -> 3389 | R96: 〇 | S96: 〇 | T96: 〇 | U96: 〇 | V96: 〇 | Z96: 〇 | AB96: 〇 | AC96: 〇 | AD96: =VLOOKUP(E96,sheet1!$B$2:$C$3209,2,FALSE) -> 返品実績入力 | AF96: 13.返品実績入力 | AG96: SA3100 | AH96: =MID(AF96,4,100) -> 返品実績入力 | AL96: =TRIM(AN96) -> 返品実績入力 | AM96: 〇 | AN96: 返品実績入力 | AO96: =TRIM(MIDB(AQ96,4,99)) -> 返品実績入力 | AP96: =TRIM(AR96) -> SA3100 | AQ96: 13.返品実績入力 | AR96: SA3100 | AS96: =TRIM(MID(AU96,4,99)) -> 返品実績入力 | AT96: =TRIM(AV96) -> SA3100 | AU96: 13.返品実績入力 | AV96: SA3100
A97: 95 | B97: 販売システム | C97: 出荷管理業務 | D97: ー | E97: SA3110 | F97: 修理実績入力 | J97: 〇 | Q97: =VLOOKUP(E97,sheet1!$B$2:$D$3209,3,FALSE) -> 8722 | R97: 〇 | S97: 〇 | T97: 〇 | U97: 〇 | V97: 〇 | Z97: 〇 | AB97: 〇 | AC97: 〇 | AD97: =VLOOKUP(E97,sheet1!$B$2:$C$3209,2,FALSE) -> 修理実績入力 | AF97: 14.修理実績入力 | AG97: SA3110 | AH97: =MID(AF97,4,100) -> 修理実績入力 | AL97: =TRIM(AN97) -> 修理実績入力 | AM97: 〇 | AN97: 修理実績入力 | AO97: =TRIM(MIDB(AQ97,4,99)) -> 修理実績入力 | AP97: =TRIM(AR97) -> SA3110 | AQ97: 14.修理実績入力 | AR97: SA3110 | AS97: =TRIM(MID(AU97,4,99)) -> 修理実績入力 | AT97: =TRIM(AV97) -> SA3110 | AU97: 14.修理実績入力 | AV97: SA3110
A98: 96 | B98: 販売システム | C98: 出荷管理業務 | D98: ー | E98: SA3190 | F98: 無償修理承認入力 | J98: 〇 | Q98: =VLOOKUP(E98,sheet1!$B$2:$D$3209,3,FALSE) -> 964 | R98: 〇 | S98: 〇 | T98: 〇 | U98: 〇 | V98: 〇 | Z98: 〇 | AB98: 〇 | AC98: 〇 | AD98: =VLOOKUP(E98,sheet1!$B$2:$C$3209,2,FALSE) -> 無償承認修理入力 | AF98: 15.無償修理承認入力 | AG98: SA3190 | AH98: =MID(AF98,4,100) -> 無償修理承認入力 | AL98: =TRIM(AN98) -> 無償修理承認入力 | AM98: 〇 | AN98: 無償修理承認入力 | AO98: =TRIM(MIDB(AQ98,4,99)) -> 無償修理承認入力 | AP98: =TRIM(AR98) -> SA3190 | AQ98: 15.無償修理承認入力 | AR98: SA3190 | AS98: =TRIM(MID(AU98,4,99)) -> 無償修理承認入力 | AT98: =TRIM(AV98) -> SA3190 | AU98: 15.無償修理承認入力 | AV98: SA3190
A99: 97 | B99: 販売システム | C99: 出荷管理業務 | D99: ー | E99: SA3220 | F99: 修理コメント訂正入力 | J99: 〇 | Q99: =VLOOKUP(E99,sheet1!$B$2:$D$3209,3,FALSE) -> 990 | R99: 〇 | S99: 〇 | T99: 〇 | U99: 〇 | V99: 〇 | Z99: 〇 | AB99: 〇 | AC99: 〇 | AD99: =VLOOKUP(E99,sheet1!$B$2:$C$3209,2,FALSE) -> 修理コメント訂正入力 | AF99: 21.修理コメント訂正入力 | AG99: SA3220 | AH99: =MID(AF99,4,100) -> 修理コメント訂正入力 | AL99: =TRIM(AN99) -> 修理コメント訂正入力 | AM99: 〇 | AN99: 修理コメント訂正入力 | AO99: =TRIM(MIDB(AQ99,4,99)) -> 修理コメント訂正入力 | AP99: =TRIM(AR99) -> SA3220 | AQ99: 21.修理コメント訂正入力 | AR99: SA3220 | AS99: =TRIM(MID(AU99,4,99)) -> 修理コメント訂正入力 | AT99: =TRIM(AV99) -> SA3220 | AU99: 21.修理コメント訂正入力 | AV99: SA3220
A100: 98 | B100: 販売システム | C100: 出荷管理業務 | D100: ー | E100: SA2310 | F100: 送り状作成（手動） | J100: 〇 | Q100: =VLOOKUP(E100,sheet1!$B$2:$D$3209,3,FALSE) -> 308 | R100: 〇 | S100: 〇 | T100: 〇 | U100: 〇 | V100: 〇 | Z100: 〇 | AB100: 〇 | AC100: 〇 | AD100: =VLOOKUP(E100,sheet1!$B$2:$C$3209,2,FALSE) -> 送り状作成指示（手動） | AF100: 51.送り状作成（手動） | AG100: SA2310 | AH100: =MID(AF100,4,100) -> 送り状作成（手動） | AL100: =TRIM(AN100) -> 送り状作成（手動） | AM100: 〇 | AN100: 送り状作成（手動） | AO100: =TRIM(MIDB(AQ100,4,99)) -> 送り状作成（手動） | AP100: =TRIM(AR100) -> SA2310 | AQ100: 51.送り状作成（手動） | AR100: SA2310 | AS100: =TRIM(MID(AU100,4,99)) -> 送り状作成（手動） | AT100: =TRIM(AV100) -> SA2310 | AU100: 51.送り状作成（手動） | AV100: SA2310
A101: 99 | B101: 販売システム | C101: 出荷管理業務 | D101: ー | E101: SA2340 | F101: 発送ﾀｯｸｼｰﾙ作成 | J101: 〇 | Q101: =VLOOKUP(E101,sheet1!$B$2:$D$3209,3,FALSE) -> 405 | R101: 〇 | S101: 〇 | T101: 〇 | U101: 〇 | V101: 〇 | Z101: 〇 | AB101: 〇 | AC101: 〇 | AD101: =VLOOKUP(E101,sheet1!$B$2:$C$3209,2,FALSE) -> 発送タックシール発行指示 | AF101: 52.発送ﾀｯｸｼｰﾙ作成 | AG101: SA2340 | AH101: =MID(AF101,4,100) -> 発送ﾀｯｸｼｰﾙ作成 | AL101: =TRIM(AN101) -> 発送ﾀｯｸｼｰﾙ作成 | AM101: 〇 | AN101: 発送ﾀｯｸｼｰﾙ作成 | AO101: =TRIM(MIDB(AQ101,4,99)) -> 発送ﾀｯｸｼｰﾙ作成 | AP101: =TRIM(AR101) -> SA2340 | AQ101: 52.発送ﾀｯｸｼｰﾙ作成 | AR101: SA2340 | AS101: =TRIM(MID(AU101,4,99)) -> 発送ﾀｯｸｼｰﾙ作成 | AT101: =TRIM(AV101) -> SA2340 | AU101: 52.発送ﾀｯｸｼｰﾙ作成 | AV101: SA2340
A102: 100 | B102: 販売システム | C102: 出荷管理業務 | D102: ー | E102: SA5140 | F102: 出荷指示データ照会 | J102: 〇 | Q102: =VLOOKUP(E102,sheet1!$B$2:$D$3209,3,FALSE) -> 392 | R102: 〇 | S102: 〇 | T102: 〇 | U102: 〇 | V102: 〇 | Z102: 〇 | AB102: 〇 | AC102: 〇 | AD102: =VLOOKUP(E102,sheet1!$B$2:$C$3209,2,FALSE) -> 出荷指示書照会 | AF102: 53.出荷指示データ照会 | AG102: SA5140 | AH102: =MID(AF102,4,100) -> 出荷指示データ照会 | AL102: =TRIM(AN102) -> 出荷指示データ照会 | AM102: 〇 | AN102: 出荷指示データ照会 | AO102: =TRIM(MIDB(AQ102,4,99)) -> 出荷指示データ照会 | AP102: =TRIM(AR102) -> SA5140 | AQ102: 53.出荷指示データ照会 | AR102: SA5140 | AS102: =TRIM(MID(AU102,4,99)) -> 出荷指示データ照会 | AT102: =TRIM(AV102) -> SA5140 | AU102: 53.出荷指示データ照会 | AV102: SA5140
A103: 101 | B103: 販売システム | C103: 出荷管理業務 | D103: ー | E103: SA5161 | F103: 修理実績照会 | J103: 〇 | Q103: =VLOOKUP(E103,sheet1!$B$2:$D$3209,3,FALSE) -> 670 | R103: 〇 | S103: 〇 | T103: 〇 | U103: 〇 | V103: 〇 | Z103: 〇 | AB103: 〇 | AC103: 〇 | AD103: =VLOOKUP(E103,sheet1!$B$2:$C$3209,2,FALSE) -> 修理実績照会（ヘッド） | AF103: 54.修理実績照会 | AG103: SA5161 | AH103: =MID(AF103,4,100) -> 修理実績照会 | AL103: =TRIM(AN103) -> 修理実績照会 | AM103: 〇 | AN103: 修理実績照会 | AO103: =TRIM(MIDB(AQ103,4,99)) -> 修理実績照会 | AP103: =TRIM(AR103) -> SA5161 | AQ103: 54.修理実績照会 | AR103: SA5161 | AS103: =TRIM(MID(AU103,4,99)) -> 修理実績照会 | AT103: =TRIM(AV103) -> SA5161 | AU103: 54.修理実績照会 | AV103: SA5161
A104: 102 | B104: 販売システム | C104: 出荷管理業務 | D104: ー | E104: SA2830 | F104: 修理内容集計表 | J104: 〇 | Q104: =VLOOKUP(E104,sheet1!$B$2:$D$3209,3,FALSE) -> 493 | R104: 〇 | S104: 〇 | T104: 〇 | U104: 〇 | V104: 〇 | Z104: 〇 | AB104: 〇 | AC104: 〇 | AD104: =VLOOKUP(E104,sheet1!$B$2:$C$3209,2,FALSE) -> 修理内容集計表 | AF104: 55.修理内容集計表 | AG104: SA2830 | AH104: =MID(AF104,4,100) -> 修理内容集計表 | AL104: =TRIM(AN104) -> 修理内容集計表 | AM104: 〇 | AN104: 修理内容集計表 | AO104: =TRIM(MIDB(AQ104,4,99)) -> 修理内容集計表 | AP104: =TRIM(AR104) -> SA2830 | AQ104: 55.修理内容集計表 | AR104: SA2830 | AS104: =TRIM(MID(AU104,4,99)) -> 修理内容集計表 | AT104: =TRIM(AV104) -> SA2830 | AU104: 55.修理内容集計表 | AV104: SA2830
A105: 103 | B105: 販売システム | C105: 出荷管理業務 | D105: ー | E105: SA2140 | F105: 代替・交換機発送伝票作成 | J105: 〇 | Q105: =VLOOKUP(E105,sheet1!$B$2:$D$3209,3,FALSE) -> 749 | R105: 〇 | S105: 〇 | T105: 〇 | U105: 〇 | V105: 〇 | Z105: 〇 | AB105: 〇 | AC105: 〇 | AD105: =VLOOKUP(E105,sheet1!$B$2:$C$3209,2,FALSE) -> 代替・交換機発送伝票作成 | AF105: 56.代替・交換機発送伝票作成 | AG105: SA2140 | AH105: =MID(AF105,4,100) -> 代替・交換機発送伝票作成 | AL105: =TRIM(AN105) -> 代替・交換機発送伝票作成 | AM105: 〇 | AN105: 代替・交換機発送伝票作成 | AO105: =TRIM(MIDB(AQ105,4,99)) -> 代替・交換機発送伝票作成 | AP105: =TRIM(AR105) -> SA2140 | AQ105: 56.代替・交換機発送伝票作成 | AR105: SA2140 | AS105: =TRIM(MID(AU105,4,99)) -> 代替・交換機発送伝票作成 | AT105: =TRIM(AV105) -> SA2140 | AU105: 56.代替・交換機発送伝票作成 | AV105: SA2140
...

Sheet sheet1
A1: 属性 | B1: オブジェクト | C1: テキスト記述 | D1: ステップ数 | E1: 頭２文字 | F1: 使用日数 | H1: 確認 | I1: =SUM(H2:H3209) -> 920 | J1: =I1/3209 -> 0.28669367 | K1: =I1/L1 -> 0.45725646 | L1: =COUNTIF(A2:A3209,"RPG") -> 2012
A2: CLP | B2: #ASPOVRC | C2: ASPしきい値オーバー時KISOサブシステム強制終了 | D2: 28 | E2: #A | F2: 2 | H2: =COUNTIF('(参考)現行システム機能階層一覧'!$E$3:$E$1048576,sheet1!B2) -> 0
A3: CLP | B3: #CHGUSR01 | C3: CHGUSRPRF ALL DISABLED (JCM JCM001 JTS MEIHO GOLD) | D3: 22 | E3: #C | F3: 4 | H3: =COUNTIF('(参考)現行システム機能階層一覧'!$E$3:$E$1048576,sheet1!B3) -> 0
A4: CLP | B4: #CHGUSR02 | C4: CHGUSRPRF ALL ENABLED (JCM JCM001 JTS MEIHO GOLD) | D4: 22 | E4: #C | F4: 4 | H4: =COUNTIF('(参考)現行システム機能階層一覧'!$E$3:$E$1048576,sheet1!B4) -> 0
A5: CLP | B5: #CRTFTP | C5: ＦＴＰデータ転送 | D5: 75 | E5: #C | F5: 48 | H5: =COUNTIF('(参考)現行システム機能階層一覧'!$E$3:$E$1048576,sheet1!B5) -> 0
A6: CLP | B6: #CRTFTP2 | C6: ＦＴＰデータ転送PC >> AS(PUT) | D6: 122 | E6: #C | F6: 258 | H6: =COUNTIF('(参考)現行システム機能階層一覧'!$E$3:$E$1048576,sheet1!B6) -> 0
A7: CLP | B7: #CRTFTP3 | C7: ＦＴＰデータ転送 メイホウ納品確認書出力用 | D7: 85 | E7: #C | F7: 111 | H7: =COUNTIF('(参考)現行システム機能階層一覧'!$E$3:$E$1048576,sheet1!B7) -> 0
A8: CLP | B8: #CRTTTO | C8: ＰＣＯＭデータ転送 ダウンロード用P31954 | D8: 149 | E8: #C | F8: 982 | H8: =COUNTIF('(参考)現行システム機能階層一覧'!$E$3:$E$1048576,sheet1!B8) -> 0
A9: CLP | B9: #CRTTTO_OR | C9: ＰＣＯＭデータ転送 ダウンロード用P31954 | D9: 142 | E9: #C | F9: 1 | H9: =COUNTIF('(参考)現行システム機能階層一覧'!$E$3:$E$1048576,sheet1!B9) -> 0
A10: CLP | B10: #DSPTAP | C10: DSPTAP ' | D10: 9 | E10: #D | F10: 1 | H10: =COUNTIF('(参考)現行システム機能階層一覧'!$E$3:$E$1048576,sheet1!B10) -> 0
A11: CLP | B11: #ENDZEND | C11: ZENDPHP7サブシステム終了 | D11: 14 | E11: #E | F11: 1682 | H11: =COUNTIF('(参考)現行システム機能階層一覧'!$E$3:$E$1048576,sheet1!B11) -> 0
A12: CLP | B12: #G7MMSP | C12: ＱＲＹ 開示区分ﾏｽﾀｰ一覧表 | D12: 36 | E12: #G | F12: 108 | H12: =COUNTIF('(参考)現行システム機能階層一覧'!$E$3:$E$1048576,sheet1!B12) -> 2
A13: CLP | B13: #G8MMSP | C13: ＱＲＹ 分類ｺｰﾄﾞﾏｽﾀｰ一覧表 | D13: 15 | E13: #G | F13: 443 | H13: =COUNTIF('(参考)現行システム機能階層一覧'!$E$3:$E$1048576,sheet1!B13) -> 1
... A3209: CLP | B3209: ZPD000C | C3209: 注残分関連製番情報 抽出 | D3209: 82 | E3209: ZP | F3209: 45 | H3209: =COUNTIF('(参考)現行システム機能階層一覧'!$E$3:$E$1048576,sheet1!B3209) -> 0
C3210: =TRIM(B3210)
